{
  "version": 0.6,
  "generator": "Overpass API 0.7.57.1 74a55df1",
  "osm3s": {
    "timestamp_osm_base": "2022-02-13T13:18:30Z",
    "timestamp_areas_base": "2022-02-13T02:36:10Z",
    "copyright": "The data included in this document is from www.openstreetmap.org. The data is made available under ODbL."
  },
  "elements": [

{
  "type": "way",
  "id": 92674454,
  "nodes": [
    1075025443,
    1075028068,
    1075028548,
    1075025584,
    1075026200
  ],
  "tags": {
    "cycleway:right": "lane",
    "highway": "primary",
    "junction": "roundabout",
    "lanes": "2",
    "maxspeed": "50",
    "name": "Rond-Point Neil Alden Armstrong"
  }
},
{
  "type": "way",
  "id": 940893619,
  "nodes": [
    1075028865,
    1075025117,
    1075025343,
    1075028027,
    1075028513,
    1075027711,
    1075026017,
    1916714705,
    1075028620,
    1075026279
  ],
  "tags": {
    "cycleway:right": "lane",
    "highway": "primary",
    "junction": "roundabout",
    "lanes": "2",
    "maxspeed": "50",
    "name": "Rond-Point Neil Alden Armstrong"
  }
},
{
  "type": "way",
  "id": 940893620,
  "nodes": [
    1075026279,
    3367664732,
    1075028356,
    1075025798,
    1075028440,
    1075025443
  ],
  "tags": {
    "cycleway:right": "lane",
    "highway": "primary",
    "junction": "roundabout",
    "lanes": "2",
    "maxspeed": "50",
    "name": "Rond-Point Neil Alden Armstrong"
  }
},
{
  "type": "way",
  "id": 940904723,
  "nodes": [
    1075026200,
    1075025161,
    1075027921,
    1075028865
  ],
  "tags": {
    "cycleway:right": "lane",
    "highway": "primary",
    "junction": "roundabout",
    "lanes": "2",
    "maxspeed": "50",
    "name": "Rond-Point Neil Alden Armstrong"
  }
},
{
  "type": "area",
  "id": 3600070070,
  "tags": {
    "admin_level": "8",
    "boundary": "administrative",
    "capital": "7",
    "name": "Béziers",
    "name:ca": "Besiers",
    "name:de": "Béziers",
    "name:fr": "Béziers",
    "name:ja": "ベジエ",
    "name:oc": "Besièrs",
    "population": "78308",
    "population:date": "2019",
    "postal_code": "34500",
    "ref:FR:SIREN": "213400328",
    "ref:INSEE": "34032",
    "source:name:oc": "ieo-bdtopoc",
    "source:population": "INSEE 2022",
    "type": "boundary",
    "website": "http://www.ville-beziers.fr/",
    "wikidata": "Q174019",
    "wikipedia": "fr:Béziers"
  }
},
{
  "type": "node",
  "id": 1075025117,
  "lat": 43.3360700,
  "lon": 3.2225473
},
{
  "type": "node",
  "id": 1075025161,
  "lat": 43.3362576,
  "lon": 3.2225565
},
{
  "type": "node",
  "id": 1075025343,
  "lat": 43.3360271,
  "lon": 3.2225897
},
{
  "type": "node",
  "id": 1075025443,
  "lat": 43.3363032,
  "lon": 3.2229445
},
{
  "type": "node",
  "id": 1075025584,
  "lat": 43.3363388,
  "lon": 3.2227014
},
{
  "type": "node",
  "id": 1075025798,
  "lat": 43.3362325,
  "lon": 3.2230168
},
{
  "type": "node",
  "id": 1075026017,
  "lat": 43.3359852,
  "lon": 3.2228838
},
{
  "type": "node",
  "id": 1075026200,
  "lat": 43.3363110,
  "lon": 3.2226246
},
{
  "type": "node",
  "id": 1075026279,
  "lat": 43.3361021,
  "lon": 3.2230262
},
{
  "type": "node",
  "id": 1075027711,
  "lat": 43.3359694,
  "lon": 3.2228001
},
{
  "type": "node",
  "id": 1075027921,
  "lat": 43.3361894,
  "lon": 3.2225211
},
{
  "type": "node",
  "id": 1075028027,
  "lat": 43.3359944,
  "lon": 3.2226467
},
{
  "type": "node",
  "id": 1075028068,
  "lat": 43.3363347,
  "lon": 3.2228705
},
{
  "type": "node",
  "id": 1075028356,
  "lat": 43.3361900,
  "lon": 3.2230341
},
{
  "type": "node",
  "id": 1075028440,
  "lat": 43.3362709,
  "lon": 3.2229864
},
{
  "type": "node",
  "id": 1075028513,
  "lat": 43.3359745,
  "lon": 3.2227140
},
{
  "type": "node",
  "id": 1075028548,
  "lat": 43.3363471,
  "lon": 3.2227864
},
{
  "type": "node",
  "id": 1075028620,
  "lat": 43.3360618,
  "lon": 3.2230018
},
{
  "type": "node",
  "id": 1075028865,
  "lat": 43.3361165,
  "lon": 3.2225238
},
{
  "type": "node",
  "id": 1916714705,
  "lat": 43.3360168,
  "lon": 3.2229510
},
{
  "type": "node",
  "id": 3367664732,
  "lat": 43.3361457,
  "lon": 3.2230373
}

  ]
}
