{
  "version": 0.6,
  "generator": "Overpass API 0.7.57.1 74a55df1",
  "osm3s": {
    "timestamp_osm_base": "2022-02-13T13:28:39Z",
    "timestamp_areas_base": "2022-02-13T06:29:09Z",
    "copyright": "The data included in this document is from www.openstreetmap.org. The data is made available under ODbL."
  },
  "elements": [

{
  "type": "node",
  "id": 671502264,
  "lat": 49.6406016,
  "lon": -1.6282447,
  "tags": {
    "bench": "yes",
    "highway": "bus_stop",
    "name": "F. Des Caveliers",
    "public_transport": "platform",
    "shelter": "yes",
    "tactile_paving": "no"
  }
},
{
  "type": "node",
  "id": 2095989973,
  "lat": 49.6262517,
  "lon": -1.6289438,
  "tags": {
    "bench": "yes",
    "bus": "yes",
    "highway": "bus_stop",
    "name": "Olympe de Gouges",
    "network": "Zéphir Bus",
    "operator": "Keolis",
    "public_transport": "platform",
    "route_ref": "1;8",
    "shelter": "yes"
  }
},
{
  "type": "node",
  "id": 2096550590,
  "lat": 49.6261507,
  "lon": -1.6287889,
  "tags": {
    "bench": "yes",
    "bus": "yes",
    "highway": "bus_stop",
    "name": "Maison Olympe de Gouges",
    "network": "Zéphir Bus",
    "operator": "Keolis",
    "public_transport": "platform",
    "route_ref": "1;8",
    "shelter": "yes"
  }
},
{
  "type": "node",
  "id": 2096555658,
  "lat": 49.6281342,
  "lon": -1.6294049,
  "tags": {
    "bench": "yes",
    "bus": "yes",
    "highway": "bus_stop",
    "name": "Champagne",
    "network": "Zéphir Bus",
    "operator": "Keolis",
    "public_transport": "platform",
    "route_ref": "1",
    "shelter": "yes"
  }
},
{
  "type": "node",
  "id": 2111991645,
  "lat": 49.6268746,
  "lon": -1.6347491,
  "tags": {
    "bench": "no",
    "bus": "yes",
    "highway": "bus_stop",
    "local_ref": "anjou",
    "name": "Anjou",
    "network": "Zéphir Bus",
    "operator": "Keolis",
    "public_transport": "platform",
    "route_ref": "8",
    "shelter": "no"
  }
},
{
  "type": "node",
  "id": 2112002813,
  "lat": 49.6282108,
  "lon": -1.6296998,
  "tags": {
    "bench": "yes",
    "bus": "yes",
    "highway": "bus_stop",
    "name": "Champagne",
    "network": "Zéphir Bus",
    "operator": "Keolis",
    "public_transport": "platform",
    "route_ref": "1",
    "shelter": "yes"
  }
},
{
  "type": "node",
  "id": 2112004794,
  "lat": 49.6285669,
  "lon": -1.6328399,
  "tags": {
    "bench": "yes",
    "highway": "bus_stop",
    "local_ref": "Maine",
    "name": "Maine",
    "network": "Zéphir Bus",
    "operator": "Keolis",
    "route_ref": "1",
    "shelter": "yes"
  }
},
{
  "type": "node",
  "id": 2112009148,
  "lat": 49.6284019,
  "lon": -1.6329739,
  "tags": {
    "bench": "yes",
    "bus": "yes",
    "highway": "bus_stop",
    "name": "Maine",
    "network": "Zéphir Bus",
    "operator": "Keolis",
    "public_transport": "platform",
    "route_ref": "1",
    "shelter": "yes"
  }
},
{
  "type": "node",
  "id": 2119066487,
  "lat": 49.6245320,
  "lon": -1.6455156,
  "tags": {
    "bench": "no",
    "bin": "no",
    "highway": "bus_stop",
    "mapillary": "238581744731455",
    "name": "Place des Justes",
    "network": "Zéphir Bus",
    "operator": "Keolis",
    "public_transport": "platform",
    "route_ref": "2",
    "shelter": "no",
    "survey:date": "2020-07-25"
  }
},
{
  "type": "node",
  "id": 2119071788,
  "lat": 49.6246558,
  "lon": -1.6452236,
  "tags": {
    "bench": "yes",
    "highway": "bus_stop",
    "name": "Place des Justes",
    "network": "Zéphir Bus",
    "operator": "Keolis",
    "route_ref": "2",
    "shelter": "yes"
  }
},
{
  "type": "node",
  "id": 2121389410,
  "lat": 49.6274916,
  "lon": -1.6354041,
  "tags": {
    "bench": "yes",
    "bus": "yes",
    "highway": "bus_stop",
    "name": "Anjou",
    "network": "Zéphir Bus",
    "operator": "Keolis",
    "public_transport": "platform",
    "route_ref": "1",
    "shelter": "yes"
  }
},
{
  "type": "node",
  "id": 2137529698,
  "lat": 49.6368958,
  "lon": -1.6257617,
  "tags": {
    "bus": "yes",
    "departures_board": "realtime",
    "highway": "bus_stop",
    "name": "Schuman",
    "public_transport": "platform",
    "shelter": "yes",
    "wheelchair": "yes"
  }
},
{
  "type": "node",
  "id": 2137556754,
  "lat": 49.6354013,
  "lon": -1.6169360,
  "tags": {
    "bus": "yes",
    "departures_board": "timetable",
    "highway": "bus_stop",
    "name": "Eleis Jacques Hebert",
    "network": "Ligne 3",
    "operator": "Zephir Bus",
    "public_transport": "platform",
    "shelter": "yes"
  }
},
{
  "type": "node",
  "id": 2137556758,
  "lat": 49.6387381,
  "lon": -1.6159360,
  "tags": {
    "bus": "yes",
    "departures_board": "timetable",
    "highway": "bus_stop",
    "name": "Place Ravenel",
    "network": "Ligne 3",
    "operator": "Zephir Bus",
    "public_transport": "platform",
    "shelter": "yes"
  }
},
{
  "type": "node",
  "id": 2144879476,
  "lat": 49.6243107,
  "lon": -1.6469434,
  "tags": {
    "bench": "no",
    "bus": "yes",
    "highway": "bus_stop",
    "name": "Coteaux",
    "network": "Cap Cotentin",
    "operator": "Communauté d'agglomération du Cotentin",
    "public_transport": "platform",
    "route_ref": "2",
    "shelter": "no",
    "type": "public_transport",
    "wheelchair": "yes"
  }
},
{
  "type": "node",
  "id": 2197513247,
  "lat": 49.6491085,
  "lon": -1.6645586,
  "tags": {
    "bus": "yes",
    "highway": "bus_stop",
    "public_transport": "platform",
    "ref": "ref:3"
  }
},
{
  "type": "node",
  "id": 2258711220,
  "lat": 49.6576885,
  "lon": -1.7094071,
  "tags": {
    "bus": "yes",
    "departures_board": "timetable",
    "highway": "bus_stop",
    "name": "Messent",
    "public_transport": "platform",
    "shelter": "no",
    "type": "public_transport",
    "wheelchair": "yes"
  }
},
{
  "type": "node",
  "id": 2258711224,
  "lat": 49.6572731,
  "lon": -1.7085749,
  "tags": {
    "bus": "yes",
    "departures_board": "timetable",
    "highway": "bus_stop",
    "name": "Messent",
    "public_transport": "platform",
    "ref": "4;5",
    "shelter": "yes",
    "type": "public_transport",
    "wheelchair": "yes"
  }
},
{
  "type": "node",
  "id": 2326598337,
  "lat": 49.6539069,
  "lon": -1.6652099,
  "tags": {
    "bus": "yes",
    "departures_board": "timetable",
    "highway": "bus_stop",
    "name": "Arago",
    "public_transport": "platform",
    "shelter": "no",
    "wheelchair": "yes"
  }
},
{
  "type": "node",
  "id": 2326598338,
  "lat": 49.6540354,
  "lon": -1.6661654,
  "tags": {
    "bus": "yes",
    "departures_board": "timetable",
    "highway": "bus_stop",
    "name": "Arago",
    "public_transport": "platform",
    "shelter": "yes",
    "wheelchair": "yes"
  }
},
{
  "type": "node",
  "id": 2326598339,
  "lat": 49.6537708,
  "lon": -1.6744340,
  "tags": {
    "bus": "yes",
    "departures_board": "timetable",
    "highway": "bus_stop",
    "name": "Brécourt",
    "public_transport": "platform",
    "shelter": "yes"
  }
},
{
  "type": "node",
  "id": 2326598340,
  "lat": 49.6537822,
  "lon": -1.6748201,
  "tags": {
    "bus": "yes",
    "departures_board": "timetable",
    "highway": "bus_stop",
    "name": "Brécourt",
    "public_transport": "platform",
    "shelter": "no"
  }
},
{
  "type": "node",
  "id": 2326598341,
  "lat": 49.6494856,
  "lon": -1.6581757,
  "tags": {
    "bus": "yes",
    "departures_board": "timetable",
    "highway": "bus_stop",
    "name": "Courbet",
    "public_transport": "platform",
    "shelter": "no"
  }
},
{
  "type": "node",
  "id": 2326598342,
  "lat": 49.6469977,
  "lon": -1.6660158,
  "tags": {
    "highway": "bus_stop",
    "name": "Danton",
    "public_transport": "platform",
    "shelter": "yes"
  }
},
{
  "type": "node",
  "id": 2326598343,
  "lat": 49.6470811,
  "lon": -1.6661562,
  "tags": {
    "highway": "bus_stop",
    "name": "Danton",
    "public_transport": "platform",
    "shelter": "no"
  }
},
{
  "type": "node",
  "id": 2326598345,
  "lat": 49.6541791,
  "lon": -1.6723144,
  "tags": {
    "bus": "yes",
    "departures_board": "timetable",
    "highway": "bus_stop",
    "name": "La Bonde",
    "public_transport": "platform",
    "shelter": "no"
  }
},
{
  "type": "node",
  "id": 2326598346,
  "lat": 49.6495801,
  "lon": -1.6606459,
  "tags": {
    "departures_board": "timetable",
    "highway": "bus_stop",
    "name": "Les Brèches",
    "network": "Zephir Bus",
    "operator": "Keolis Cherbourg",
    "public_transport": "platform",
    "shelter": "no"
  }
},
{
  "type": "node",
  "id": 2326598347,
  "lat": 49.6496727,
  "lon": -1.6607977,
  "tags": {
    "bus": "yes",
    "departures_board": "timetable",
    "highway": "bus_stop",
    "name": "Les Brèches",
    "network": "Zephir Bus",
    "operator": "Keolis Cherbourg",
    "public_transport": "platform",
    "shelter": "yes"
  }
},
{
  "type": "node",
  "id": 2326598348,
  "lat": 49.6511148,
  "lon": -1.6606589,
  "tags": {
    "bus": "yes",
    "departures_board": "timetable",
    "highway": "bus_stop",
    "name": "Couplets",
    "network": "Zephir Bus",
    "operator": "Keolis Cherbourg",
    "public_transport": "platform",
    "shelter": "no"
  }
},
{
  "type": "node",
  "id": 2326598349,
  "lat": 49.6515431,
  "lon": -1.6604529,
  "tags": {
    "bus": "yes",
    "departures_board": "timetable",
    "highway": "bus_stop",
    "name": "Couplets",
    "public_transport": "platform",
    "shelter": "no"
  }
},
{
  "type": "node",
  "id": 2326598350,
  "lat": 49.6490100,
  "lon": -1.6644738,
  "tags": {
    "highway": "bus_stop",
    "name": "Longues Pierres",
    "public_transport": "platform",
    "shelter": "no"
  }
},
{
  "type": "node",
  "id": 2326598351,
  "lat": 49.6491097,
  "lon": -1.6646711,
  "tags": {
    "highway": "bus_stop",
    "name": "Longues Pierres",
    "public_transport": "platform",
    "shelter": "yes"
  }
},
{
  "type": "node",
  "id": 2326598352,
  "lat": 49.6468162,
  "lon": -1.6438418,
  "tags": {
    "bench": "yes",
    "bin": "yes",
    "highway": "bus_stop",
    "lit": "yes",
    "name": "Hôtel des Impôts",
    "public_transport": "platform",
    "shelter": "yes",
    "tactile_paving": "no"
  }
},
{
  "type": "node",
  "id": 2326598355,
  "lat": 49.6531189,
  "lon": -1.6624881,
  "tags": {
    "bus": "yes",
    "departures_board": "timetable",
    "highway": "bus_stop",
    "name": "Prévert",
    "network": "Zephir Bus",
    "operator": "Keolis Cherbourg",
    "public_transport": "platform",
    "shelter": "no"
  }
},
{
  "type": "node",
  "id": 2326598356,
  "lat": 49.6480479,
  "lon": -1.6487178,
  "tags": {
    "bench": "no",
    "bin": "no",
    "highway": "bus_stop",
    "lit": "yes",
    "name": "République",
    "public_transport": "platform",
    "shelter": "no",
    "tactile_paving": "no"
  }
},
{
  "type": "node",
  "id": 2326598357,
  "lat": 49.6503472,
  "lon": -1.6516110,
  "tags": {
    "bus": "yes",
    "highway": "bus_stop",
    "name": "Terrasses",
    "network": "Zéphir Bus",
    "operator": "Communauté d'agglomération du Cotentin",
    "public_transport": "platform",
    "shelter": "yes",
    "wheelchair": "yes"
  }
},
{
  "type": "node",
  "id": 2326598358,
  "lat": 49.6478492,
  "lon": -1.6608817,
  "tags": {
    "highway": "bus_stop",
    "name": "Vigny",
    "public_transport": "platform"
  }
},
{
  "type": "node",
  "id": 2326598359,
  "lat": 49.6479736,
  "lon": -1.6681043,
  "tags": {
    "highway": "bus_stop",
    "name": "Zola",
    "public_transport": "platform",
    "shelter": "no"
  }
},
{
  "type": "node",
  "id": 2490620768,
  "lat": 49.6384255,
  "lon": -1.6278576,
  "tags": {
    "bench": "yes",
    "bus": "yes",
    "highway": "bus_stop",
    "name": "Place Henry Gréville",
    "public_transport": "platform",
    "ref": "3; 4; 5",
    "shelter": "yes",
    "tactile_paving": "no"
  }
},
{
  "type": "node",
  "id": 2611919775,
  "lat": 49.6607541,
  "lon": -1.6973204,
  "tags": {
    "bench": "yes",
    "bus": "yes",
    "departures_board": "timetable",
    "highway": "bus_stop",
    "name": "Paul Bert",
    "network": "Cap Cotentin",
    "operator": "Communauté d'agglomération du Cotentin",
    "public_transport": "platform",
    "shelter": "yes",
    "wheelchair": "yes"
  }
},
{
  "type": "node",
  "id": 2784770104,
  "lat": 49.6282620,
  "lon": -1.6395612,
  "tags": {
    "bus": "yes",
    "highway": "bus_stop",
    "name": "Becquerel",
    "network": "Zéphir Bus",
    "operator": "Keolis",
    "public_transport": "platform",
    "ref": "1;8",
    "route_ref": "1;8"
  }
},
{
  "type": "node",
  "id": 2784770105,
  "lat": 49.6283954,
  "lon": -1.6394873,
  "tags": {
    "bus": "yes",
    "highway": "bus_stop",
    "name": "Becquerel",
    "network": "Zéphir Bus",
    "operator": "Keolis",
    "public_transport": "platform",
    "ref": "1;8",
    "route_ref": "1;8"
  }
},
{
  "type": "node",
  "id": 3025324744,
  "lat": 49.6444180,
  "lon": -1.6337554,
  "tags": {
    "bench": "yes",
    "bus": "no",
    "highway": "bus_stop",
    "name": "Arsenal",
    "public_transport": "platform",
    "shelter": "yes",
    "tactile_paving": "no"
  }
},
{
  "type": "node",
  "id": 3025324745,
  "lat": 49.6445968,
  "lon": -1.6313281,
  "tags": {
    "bench": "yes",
    "bus": "no",
    "highway": "bus_stop",
    "name": "Arsenal",
    "public_transport": "platform",
    "ref": "3;5",
    "shelter": "yes",
    "tactile_paving": "yes"
  }
},
{
  "type": "node",
  "id": 3057004478,
  "lat": 49.6433547,
  "lon": -1.6291182,
  "tags": {
    "bench": "yes",
    "bus": "yes",
    "highway": "bus_stop",
    "lit": "yes",
    "name": "Chantier",
    "public_transport": "platform",
    "shelter": "yes",
    "tactile_paving": "no"
  }
},
{
  "type": "node",
  "id": 3057004479,
  "lat": 49.6434660,
  "lon": -1.6285373,
  "tags": {
    "bench": "yes",
    "bus": "no",
    "highway": "bus_stop",
    "lit": "yes",
    "name": "Chantier",
    "public_transport": "platform",
    "shelter": "yes",
    "tactile_paving": "no"
  }
},
{
  "type": "node",
  "id": 3057822670,
  "lat": 49.6620002,
  "lon": -1.6958990,
  "tags": {
    "bus": "yes",
    "highway": "bus_stop",
    "name": "Mairie",
    "public_transport": "platform",
    "shelter": "yes",
    "wheelchair": "yes"
  }
},
{
  "type": "node",
  "id": 3102907979,
  "lat": 49.6398462,
  "lon": -1.6018179,
  "tags": {
    "bench": "yes",
    "bin": "no",
    "bus": "yes",
    "departures_board": "timetable",
    "highway": "bus_stop",
    "name": "Guérranderie",
    "network": "Cap Cotentin",
    "operator": "Communauté d'agglomération du Cotentin",
    "public_transport": "platform",
    "shelter": "yes",
    "wheelchair": "yes"
  }
},
{
  "type": "node",
  "id": 3109738483,
  "lat": 49.6539358,
  "lon": -1.6818722,
  "tags": {
    "highway": "bus_stop",
    "name": "Carné",
    "public_transport": "platform",
    "shelter": "yes",
    "source": "cadastre-dgi-fr source : Direction Générale des Impôts - Cadastre. Mise à jour : 2014"
  }
},
{
  "type": "node",
  "id": 3109738484,
  "lat": 49.6541375,
  "lon": -1.6777333,
  "tags": {
    "highway": "bus_stop",
    "name": "Houlgatte",
    "public_transport": "platform",
    "shelter": "yes",
    "source": "cadastre-dgi-fr source : Direction Générale des Impôts - Cadastre. Mise à jour : 2014"
  }
},
{
  "type": "node",
  "id": 3109738485,
  "lat": 49.6542552,
  "lon": -1.6777804,
  "tags": {
    "highway": "bus_stop",
    "name": "Houlgatte",
    "public_transport": "platform",
    "shelter": "yes",
    "source": "cadastre-dgi-fr source : Direction Générale des Impôts - Cadastre. Mise à jour : 2014"
  }
},
{
  "type": "node",
  "id": 3109738487,
  "lat": 49.6569695,
  "lon": -1.6737591,
  "tags": {
    "bench": "yes",
    "bin": "yes",
    "bus": "yes",
    "departures_board": "timetable",
    "highway": "bus_stop",
    "name": "Surcouf",
    "network": "Cap Cotentin",
    "operator": "Communauté d'agglomération du Cotentin",
    "public_transport": "platform",
    "shelter": "yes",
    "source": "cadastre-dgi-fr source : Direction Générale des Impôts - Cadastre. Mise à jour : 2014",
    "wheelchair": "yes"
  }
},
{
  "type": "node",
  "id": 3109738488,
  "lat": 49.6570745,
  "lon": -1.6732183,
  "tags": {
    "bench": "yes",
    "bin": "yes",
    "bus": "yes",
    "departures_board": "timetable",
    "highway": "bus_stop",
    "name": "Surcouf",
    "network": "Cap Cotentin",
    "operator": "Communauté d'agglomération du Cotentin",
    "public_transport": "platform",
    "shelter": "yes",
    "source": "cadastre-dgi-fr source : Direction Générale des Impôts - Cadastre. Mise à jour : 2014",
    "wheelchair": "yes"
  }
},
{
  "type": "node",
  "id": 3439384863,
  "lat": 49.6480072,
  "lon": -1.6488122,
  "tags": {
    "bench": "no",
    "bin": "yes",
    "highway": "bus_stop",
    "lit": "yes",
    "name": "République",
    "public_transport": "platform",
    "shelter": "no",
    "tactile_paving": "no"
  }
},
{
  "type": "node",
  "id": 3487006450,
  "lat": 49.6454904,
  "lon": -1.6511692,
  "tags": {
    "bus": "yes",
    "departures_board": "timetable",
    "highway": "bus_stop",
    "name": "Église",
    "public_transport": "platform",
    "shelter": "no",
    "source": "Survey"
  }
},
{
  "type": "node",
  "id": 3487006451,
  "lat": 49.6455644,
  "lon": -1.6512231,
  "tags": {
    "bus": "yes",
    "departures_board": "timetable",
    "highway": "bus_stop",
    "name": "Église",
    "public_transport": "platform",
    "shelter": "yes",
    "source": "Survey"
  }
},
{
  "type": "node",
  "id": 3827566067,
  "lat": 49.6572885,
  "lon": -1.6888107,
  "tags": {
    "highway": "bus_stop",
    "name": "Albert Thomas",
    "public_transport": "platform",
    "shelter": "yes"
  }
},
{
  "type": "node",
  "id": 3827566068,
  "lat": 49.6574102,
  "lon": -1.6887910,
  "tags": {
    "highway": "bus_stop",
    "name": "Albert Thomas",
    "public_transport": "platform"
  }
},
{
  "type": "node",
  "id": 3827566069,
  "lat": 49.6598947,
  "lon": -1.7153013,
  "tags": {
    "bench": "yes",
    "departures_board": "timetable",
    "highway": "bus_stop",
    "name": "Amfreville",
    "public_transport": "platform",
    "route_ref": "4;5",
    "wheelchair": "yes"
  }
},
{
  "type": "node",
  "id": 3827566070,
  "lat": 49.6058892,
  "lon": -1.5992591,
  "tags": {
    "bus": "yes",
    "highway": "bus_stop",
    "name": "Marettes",
    "public_transport": "platform",
    "shelter": "no",
    "wheelchair": "yes"
  }
},
{
  "type": "node",
  "id": 3827566071,
  "lat": 49.6058777,
  "lon": -1.5989609,
  "tags": {
    "bench": "no",
    "bin": "no",
    "bus": "yes",
    "departures_board": "timetable",
    "highway": "bus_stop",
    "mapillary": "222345619323280",
    "name": "Marettes",
    "public_transport": "platform",
    "shelter": "no",
    "survey:date": "2020-07-25",
    "wheelchair": "yes"
  }
},
{
  "type": "node",
  "id": 3827566072,
  "lat": 49.6249667,
  "lon": -1.6166856,
  "tags": {
    "bench": "yes",
    "bus": "yes",
    "departures_board": "timetable",
    "highway": "bus_stop",
    "name": "Octroi du Roule",
    "public_transport": "platform",
    "shelter": "yes"
  }
},
{
  "type": "node",
  "id": 3827566073,
  "lat": 49.6263853,
  "lon": -1.6171979,
  "tags": {
    "bench": "yes",
    "bin": "yes",
    "bus": "yes",
    "departures_board": "timetable",
    "highway": "bus_stop",
    "name": "Octroi du Roule",
    "network": "Zephir Bus",
    "operator": "Aglo du Cotentin",
    "public_transport": "platform",
    "shelter": "yes"
  }
},
{
  "type": "node",
  "id": 3827566075,
  "lat": 49.6550688,
  "lon": -1.6864234,
  "tags": {
    "highway": "bus_stop",
    "name": "Schaffner",
    "public_transport": "platform",
    "shelter": "no"
  }
},
{
  "type": "node",
  "id": 3827566076,
  "lat": 49.6554672,
  "lon": -1.6867947,
  "tags": {
    "highway": "bus_stop",
    "name": "Schaffner",
    "public_transport": "platform",
    "shelter": "no"
  }
},
{
  "type": "node",
  "id": 3827566077,
  "lat": 49.6416197,
  "lon": -1.6370799,
  "tags": {
    "highway": "bus_stop",
    "name": "Stade",
    "public_transport": "platform",
    "shelter": "yes",
    "source": "cadastre-dgi-fr source : Direction Générale des Impôts - Cadastre. Mise à jour : 2014"
  }
},
{
  "type": "node",
  "id": 3827566078,
  "lat": 49.6423871,
  "lon": -1.6368290,
  "tags": {
    "highway": "bus_stop",
    "name": "Stade",
    "public_transport": "platform",
    "shelter": "yes",
    "source": "cadastre-dgi-fr source : Direction Générale des Impôts - Cadastre. Mise à jour : 2014"
  }
},
{
  "type": "node",
  "id": 3871465534,
  "lat": 49.6635890,
  "lon": -1.6850370,
  "tags": {
    "bench": "yes",
    "bin": "yes",
    "bus": "yes",
    "departures_board": "timetable",
    "highway": "bus_stop",
    "name": "Dixmude",
    "network": "Cap Cotentin",
    "operator": "Communauté d'agglomération du Cotentin",
    "public_transport": "platform",
    "shelter": "yes",
    "wheelchair": "yes"
  }
},
{
  "type": "node",
  "id": 3871465535,
  "lat": 49.6641085,
  "lon": -1.6852732,
  "tags": {
    "bench": "no",
    "bin": "yes",
    "bus": "yes",
    "departures_board": "timetable",
    "highway": "bus_stop",
    "name": "Dixmude",
    "network": "Cap Cotention",
    "operator": "Communauté d'agglomération du Cotentin",
    "public_transport": "platform",
    "shelter": "no",
    "wheelchair": "yes"
  }
},
{
  "type": "node",
  "id": 3902489227,
  "lat": 49.6336774,
  "lon": -1.6365874,
  "tags": {
    "bench": "no",
    "highway": "bus_stop",
    "name": "Redoute",
    "public_transport": "platform",
    "route_ref": "2",
    "shelter": "no"
  }
},
{
  "type": "node",
  "id": 3902489228,
  "lat": 49.6339651,
  "lon": -1.6360762,
  "tags": {
    "bench": "no",
    "highway": "bus_stop",
    "name": "Redoute",
    "network": "Zéphir Bus",
    "operator": "Keolis",
    "public_transport": "platform",
    "route_ref": "2",
    "shelter": "no"
  }
},
{
  "type": "node",
  "id": 3919050780,
  "lat": 49.6467797,
  "lon": -1.6442698,
  "tags": {
    "bench": "yes",
    "bin": "yes",
    "bus": "yes",
    "highway": "bus_stop",
    "lit": "yes",
    "name": "Hôtel des Impôts",
    "public_transport": "platform",
    "route_ref": "3;5;D",
    "shelter": "yes",
    "tactile_paving": "no",
    "type": "public_transport"
  }
},
{
  "type": "node",
  "id": 3921425208,
  "lat": 49.6358259,
  "lon": -1.6565078,
  "tags": {
    "bus": "yes",
    "departures_board": "timetable",
    "highway": "bus_stop",
    "name": "Polyclinique",
    "network": "Cap Cotentin",
    "operator": "Communauté d'agglomération du Cotentin",
    "public_transport": "platform",
    "route_ref": "8",
    "shelter": "no",
    "wheelchair": "limited"
  }
},
{
  "type": "node",
  "id": 3954582884,
  "lat": 49.6370110,
  "lon": -1.6393017,
  "tags": {
    "bus": "yes",
    "highway": "bus_stop",
    "name": "Les Aiguillons",
    "network": "Zéphir Bus",
    "operator": "Keolis",
    "public_transport": "platform",
    "route_ref": "1"
  }
},
{
  "type": "node",
  "id": 3954582885,
  "lat": 49.6371342,
  "lon": -1.6392308,
  "tags": {
    "bench": "no",
    "bus": "yes",
    "highway": "bus_stop",
    "name": "Les Aiguillons",
    "network": "Zéphir Bus",
    "operator": "Keolis",
    "public_transport": "platform",
    "route_ref": "1"
  }
},
{
  "type": "node",
  "id": 3954582888,
  "lat": 49.6591385,
  "lon": -1.6916815,
  "tags": {
    "bench": "yes",
    "bin": "yes",
    "bus": "yes",
    "departures_board": "timetable",
    "highway": "bus_stop",
    "name": "Collège Ferry",
    "public_transport": "platform",
    "shelter": "yes",
    "wheelchair": "yes"
  }
},
{
  "type": "node",
  "id": 3954582889,
  "lat": 49.6594918,
  "lon": -1.6919669,
  "tags": {
    "bench": "yes",
    "bin": "no",
    "bus": "yes",
    "departures_board": "timetable",
    "highway": "bus_stop",
    "name": "Collège Ferry",
    "network": "Cap Cotentin",
    "operator": "Communauté d'agglomération du Cotentin",
    "public_transport": "platform",
    "shelter": "yes",
    "wheelchair": "yes"
  }
},
{
  "type": "node",
  "id": 3954582890,
  "lat": 49.6646205,
  "lon": -1.6880852,
  "tags": {
    "bench": "yes",
    "bin": "yes",
    "departures_board": "timetable",
    "highway": "bus_stop",
    "name": "Epinay Bas",
    "network": "Cap Cotentin",
    "operator": "Communauté d'agglomération du Cotentin",
    "public_transport": "platform",
    "shelter": "yes",
    "wheelchair": "no"
  }
},
{
  "type": "node",
  "id": 3954582891,
  "lat": 49.6647362,
  "lon": -1.6880261,
  "tags": {
    "bench": "no",
    "bin": "no",
    "bus": "yes",
    "departures_board": "timetable",
    "highway": "bus_stop",
    "name": "Epinay Bas",
    "network": "Cap Cotentin",
    "operator": "Communauté d'agglomération du Cotentin",
    "public_transport": "platform",
    "shelter": "no",
    "wheelchair": "no"
  }
},
{
  "type": "node",
  "id": 3954582892,
  "lat": 49.6639985,
  "lon": -1.6912574,
  "tags": {
    "bench": "yes",
    "bin": "yes",
    "bus": "yes",
    "departures_board": "timetable",
    "highway": "bus_stop",
    "name": "Epinay Centre",
    "network": "Cap Cotentin",
    "operator": "Communauté d'agglomération du Cotentin",
    "public_transport": "platform",
    "shelter": "yes",
    "wheelchair": "yes"
  }
},
{
  "type": "node",
  "id": 3954582893,
  "lat": 49.6639715,
  "lon": -1.6919728,
  "tags": {
    "bench": "no",
    "bin": "no",
    "bus": "yes",
    "departures_board": "timetable",
    "highway": "bus_stop",
    "name": "Epinay Centre",
    "network": "Cap Cotentin",
    "operator": "Communauté d'agglomération du Cotentin",
    "public_transport": "platform",
    "shelter": "no",
    "wheelchair": "yes"
  }
},
{
  "type": "node",
  "id": 3954582894,
  "lat": 49.6603424,
  "lon": -1.6798115,
  "tags": {
    "bench": "yes",
    "bin": "yes",
    "bus": "yes",
    "departures_board": "timetable",
    "highway": "bus_stop",
    "name": "Petite Auberge",
    "network": "Cap Cotentin",
    "operator": "Communauté d'agglomération du Cotentin",
    "public_transport": "platform",
    "shelter": "yes",
    "wheelchair": "no"
  }
},
{
  "type": "node",
  "id": 3954582895,
  "lat": 49.6608703,
  "lon": -1.6803018,
  "tags": {
    "bench": "no",
    "bin": "no",
    "bus": "yes",
    "departures_board": "timetable",
    "highway": "bus_stop",
    "name": "Petite Auberge",
    "network": "Cap Cotentin",
    "operator": "Communauté d'agglomération du Cotentin",
    "public_transport": "platform",
    "shelter": "no",
    "wheelchair": "no"
  }
},
{
  "type": "node",
  "id": 3954582896,
  "lat": 49.6280167,
  "lon": -1.6420495,
  "tags": {
    "bus": "yes",
    "departures_board": "timetable",
    "highway": "bus_stop",
    "name": "Rossel",
    "network": "Cap Cotentin",
    "operator": "Keolis",
    "public_transport": "platform",
    "route_ref": "2",
    "shelter": "no",
    "wheelchair": "yes"
  }
},
{
  "type": "node",
  "id": 3954582897,
  "lat": 49.6283869,
  "lon": -1.6415778,
  "tags": {
    "bench": "no",
    "bin": "no",
    "highway": "bus_stop",
    "mapillary": "308621147490283",
    "name": "Rossel",
    "network": "ZéphirBus",
    "operator": "Keolis",
    "public_transport": "platform",
    "route_ref": "2",
    "shelter": "no",
    "survey:date": "2020-07-25"
  }
},
{
  "type": "node",
  "id": 3954582898,
  "lat": 49.6614052,
  "lon": -1.6940273,
  "tags": {
    "highway": "bus_stop",
    "name": "Stade Fernagu",
    "public_transport": "platform"
  }
},
{
  "type": "node",
  "id": 3954582899,
  "lat": 49.6615432,
  "lon": -1.6941180,
  "tags": {
    "highway": "bus_stop",
    "name": "Stade Fernagu",
    "public_transport": "platform"
  }
},
{
  "type": "node",
  "id": 3954582920,
  "lat": 49.6316863,
  "lon": -1.6383305,
  "tags": {
    "bus": "yes",
    "highway": "bus_stop",
    "name": "Voltaire",
    "network": "Zéphir Bus",
    "operator": "Keolis",
    "public_transport": "platform",
    "route_ref": "2"
  }
},
{
  "type": "node",
  "id": 3987383285,
  "lat": 49.6570336,
  "lon": -1.6661647,
  "tags": {
    "bench": "yes",
    "bin": "yes",
    "bus": "yes",
    "departures_board": "timetable",
    "highway": "bus_stop",
    "name": "Capel",
    "network": "Cap Cotentin",
    "operator": "Communauté d'agglomération du Cotentin",
    "public_transport": "platform",
    "shelter": "yes",
    "wheelchair": "yes"
  }
},
{
  "type": "node",
  "id": 3987383286,
  "lat": 49.6571369,
  "lon": -1.6662734,
  "tags": {
    "bench": "yes",
    "bin": "yes",
    "bus": "yes",
    "departures_board": "timetable",
    "highway": "bus_stop",
    "name": "Capel",
    "network": "Cap Cotentin",
    "operator": "Communauté d'agglomération du Cotentin",
    "public_transport": "platform",
    "shelter": "yes",
    "wheelchair": "yes"
  }
},
{
  "type": "node",
  "id": 3987383290,
  "lat": 49.6528153,
  "lon": -1.6539163,
  "tags": {
    "bench": "yes",
    "bin": "yes",
    "departures_board": "timetable",
    "highway": "bus_stop",
    "name": "La Paix",
    "network": "Cap Cotentin",
    "operator": "Communauté d'agglomération du Cotentin",
    "public_transport": "platform",
    "shelter": "yes",
    "wheelchair": "yes"
  }
},
{
  "type": "node",
  "id": 3987383291,
  "lat": 49.6531683,
  "lon": -1.6541088,
  "tags": {
    "bench": "no",
    "bin": "yes",
    "bus": "yes",
    "departures_board": "timetable",
    "highway": "bus_stop",
    "name": "La Paix",
    "network": "Cap Cotentin",
    "operator": "Communauté d'agglomération du Cotentin",
    "public_transport": "platform",
    "shelter": "no",
    "wheelchair": "yes"
  }
},
{
  "type": "node",
  "id": 4065830701,
  "lat": 49.6547273,
  "lon": -1.6557423,
  "tags": {
    "bench": "no",
    "bin": "no",
    "bus": "yes",
    "departures_board": "timetable",
    "highway": "bus_stop",
    "name": "Chasse Mitais",
    "network": "Cap Cotentin",
    "operator": "Communauté d'agglomération du Cotentin",
    "public_transport": "platform",
    "shelter": "no",
    "wheelchair": "yes"
  }
},
{
  "type": "node",
  "id": 4065830702,
  "lat": 49.6354121,
  "lon": -1.6363356,
  "tags": {
    "bench": "no",
    "highway": "bus_stop",
    "name": "Cimetière",
    "network": "Zéphir Bus",
    "operator": "Keolis",
    "public_transport": "platform",
    "route_ref": "2",
    "shelter": "no"
  }
},
{
  "type": "node",
  "id": 4065830703,
  "lat": 49.6355555,
  "lon": -1.6363325,
  "tags": {
    "bench": "yes",
    "highway": "bus_stop",
    "name": "Cimetière",
    "network": "Zéphir Bus",
    "operator": "Keolis",
    "public_transport": "platform",
    "route_ref": "2",
    "shelter": "yes"
  }
},
{
  "type": "node",
  "id": 4065830704,
  "lat": 49.6314967,
  "lon": -1.6501703,
  "tags": {
    "highway": "bus_stop",
    "name": "Complexe Sportif",
    "public_transport": "platform"
  }
},
{
  "type": "node",
  "id": 4065830706,
  "lat": 49.6435757,
  "lon": -1.6645665,
  "tags": {
    "bus": "yes",
    "highway": "bus_stop",
    "name": "Les Lavandes",
    "network": "Zéphir Bus",
    "operator": "Communauté d'agglomération du Cotentin",
    "public_transport": "platform"
  }
},
{
  "type": "node",
  "id": 4065830707,
  "lat": 49.6261641,
  "lon": -1.6439092,
  "tags": {
    "bench": "no",
    "bin": "no",
    "highway": "bus_stop",
    "mapillary": "127085006060730",
    "name": "Salengro",
    "network": "Zéphir Bus",
    "operator": "Keolis",
    "public_transport": "platform",
    "route_ref": "2",
    "shelter": "no",
    "survey:date": "2020-07-25"
  }
},
{
  "type": "node",
  "id": 4065830708,
  "lat": 49.6265628,
  "lon": -1.6433860,
  "tags": {
    "bench": "no",
    "bin": "yes",
    "highway": "bus_stop",
    "mapillary": "145907894217712",
    "name": "Salengro",
    "network": "Zéphir Bus",
    "operator": "Keolis",
    "public_transport": "platform",
    "route_ref": "2",
    "shelter": "no",
    "survey:date": "2020-07-25"
  }
},
{
  "type": "node",
  "id": 4152566137,
  "lat": 49.6340372,
  "lon": -1.6230996,
  "tags": {
    "bus": "yes",
    "highway": "bus_stop",
    "name": "Mendès France",
    "network": "Zéphir Bus",
    "operator": "Communauté d'agglomération du Cotentin",
    "public_transport": "platform",
    "shelter": "yes",
    "source": "cadastre-dgi-fr source : Direction Générale des Impôts - Cadastre. Mise à jour : 2014",
    "wheelchair": "yes"
  }
},
{
  "type": "node",
  "id": 4574956790,
  "lat": 49.6320562,
  "lon": -1.6177427,
  "tags": {
    "bench": "yes",
    "bin": "yes",
    "bus": "yes",
    "departures_board": "timetable",
    "highway": "bus_stop",
    "lit": "yes",
    "name": "Jardin Public",
    "public_transport": "platform",
    "shelter": "yes",
    "tactile_paving": "no"
  }
},
{
  "type": "node",
  "id": 4723106490,
  "lat": 49.6573439,
  "lon": -1.7053895,
  "tags": {
    "bus": "yes",
    "highway": "bus_stop",
    "name": "Les Mourets",
    "public_transport": "platform",
    "shelter": "no",
    "wheelchair": "yes"
  }
},
{
  "type": "node",
  "id": 4743951967,
  "lat": 49.6457216,
  "lon": -1.6385761,
  "tags": {
    "bench": "yes",
    "bin": "yes",
    "bus": "yes",
    "highway": "bus_stop",
    "name": "Hôpital Maritime",
    "public_transport": "platform",
    "route_ref": "3;5",
    "shelter": "yes",
    "type": "public_transport"
  }
},
{
  "type": "node",
  "id": 4743951985,
  "lat": 49.6302322,
  "lon": -1.6440095,
  "tags": {
    "bus": "yes",
    "highway": "bus_stop",
    "name": "Branly",
    "network": "Zéphir Bus",
    "operator": "Keolis",
    "public_transport": "platform",
    "ref": "Branly",
    "route_ref": "1;8"
  }
},
{
  "type": "node",
  "id": 4743951986,
  "lat": 49.6312077,
  "lon": -1.6464336,
  "tags": {
    "bus": "yes",
    "highway": "bus_stop",
    "name": "Bayet",
    "network": "Zéphir Bus",
    "operator": "Keolis",
    "public_transport": "platform",
    "ref": "Bayet",
    "route_ref": "1"
  }
},
{
  "type": "node",
  "id": 4743951987,
  "lat": 49.6312713,
  "lon": -1.6463097,
  "tags": {
    "bus": "yes",
    "highway": "bus_stop",
    "name": "Bayet",
    "network": "Zéphir Bus",
    "operator": "Keolis",
    "public_transport": "platform",
    "ref": "Bayet",
    "route_ref": "1"
  }
},
{
  "type": "node",
  "id": 4743951988,
  "lat": 49.6298422,
  "lon": -1.6427236,
  "tags": {
    "bus": "yes",
    "highway": "bus_stop",
    "name": "Branly",
    "network": "Zéphir Bus",
    "operator": "Keolis",
    "public_transport": "platform",
    "ref": "Branly",
    "route_ref": "1;8"
  }
},
{
  "type": "node",
  "id": 4805457350,
  "lat": 49.6582008,
  "lon": -1.6769996,
  "tags": {
    "highway": "bus_stop",
    "name": "Hameau de la Mer",
    "public_transport": "platform"
  }
},
{
  "type": "node",
  "id": 4805457351,
  "lat": 49.6582048,
  "lon": -1.6768579,
  "tags": {
    "highway": "bus_stop",
    "name": "Hameau de la Mer",
    "public_transport": "platform"
  }
},
{
  "type": "node",
  "id": 4971514073,
  "lat": 49.6456738,
  "lon": -1.6393634,
  "tags": {
    "bench": "yes",
    "bus": "yes",
    "highway": "bus_stop",
    "name": "Hôpital Maritime",
    "public_transport": "platform",
    "route_ref": "3;5;D",
    "shelter": "yes",
    "type": "public_transport"
  }
},
{
  "type": "node",
  "id": 4971514074,
  "lat": 49.6335984,
  "lon": -1.6205338,
  "tags": {
    "bench": "yes",
    "bus": "yes",
    "departures_board": "realtime",
    "highway": "bus_stop",
    "name": "Gare SNCF",
    "public_transport": "platform",
    "shelter": "yes",
    "tactile_paving": "yes",
    "wheelchair": "yes"
  }
},
{
  "type": "node",
  "id": 4971514094,
  "lat": 49.6080497,
  "lon": -1.6110655,
  "tags": {
    "bench": "no",
    "bin": "no",
    "bus": "yes",
    "highway": "bus_stop",
    "name": "Les Renardières",
    "public_transport": "platform",
    "ref": "4",
    "shelter": "no"
  }
},
{
  "type": "node",
  "id": 5275263821,
  "lat": 49.6084814,
  "lon": -1.6156215,
  "tags": {
    "bench": "no",
    "bin": "no",
    "bus": "yes",
    "highway": "bus_stop",
    "name": "La Loge",
    "public_transport": "platform",
    "shelter": "no"
  }
},
{
  "type": "node",
  "id": 5275263822,
  "lat": 49.6085122,
  "lon": -1.6155053,
  "tags": {
    "bench": "no",
    "bin": "no",
    "bus": "yes",
    "highway": "bus_stop",
    "name": "La Loge",
    "public_transport": "platform",
    "shelter": "yes"
  }
},
{
  "type": "node",
  "id": 5365538770,
  "lat": 49.6426836,
  "lon": -1.6249989,
  "tags": {
    "bench": "yes",
    "bus": "yes",
    "highway": "bus_stop",
    "name": "Hôtel de Ville",
    "public_transport": "platform",
    "shelter": "yes",
    "tactile_paving": "no"
  }
},
{
  "type": "node",
  "id": 5844727737,
  "lat": 49.6420098,
  "lon": -1.6176919,
  "tags": {
    "highway": "bus_stop",
    "name": "Ferry Bus Stop",
    "shelter": "no"
  }
},
{
  "type": "node",
  "id": 6163545864,
  "lat": 49.6160604,
  "lon": -1.6027839,
  "tags": {
    "bench": "no",
    "bin": "no",
    "bus": "yes",
    "departures_board": "timetable",
    "highway": "bus_stop",
    "name": "H. Cornat",
    "public_transport": "platform",
    "shelter": "no",
    "wheelchair": "yes"
  }
},
{
  "type": "node",
  "id": 6258388989,
  "lat": 49.6402371,
  "lon": -1.6457398,
  "tags": {
    "bus": "yes",
    "highway": "bus_stop",
    "name": "Les Fourches",
    "network": "Zéphir Bus",
    "operator": "Keolis",
    "public_transport": "platform",
    "route_ref": "1",
    "shelter": "yes",
    "wheelchair": "yes"
  }
},
{
  "type": "node",
  "id": 6258403316,
  "lat": 49.6400279,
  "lon": -1.6424815,
  "tags": {
    "bus": "yes",
    "highway": "bus_stop",
    "name": "Millet",
    "network": "Zéphir Bus",
    "operator": "Keolis",
    "public_transport": "platform",
    "ref": "Millet",
    "route_ref": "1"
  }
},
{
  "type": "node",
  "id": 6258435080,
  "lat": 49.6398179,
  "lon": -1.6397350,
  "tags": {
    "bench": "no",
    "bin": "no",
    "bus": "yes",
    "highway": "bus_stop",
    "lit": "yes",
    "name": "Le Conquérant",
    "public_transport": "platform",
    "ref": "Le Conquérant",
    "route_ref": "1;4",
    "shelter": "no",
    "tactile_paving": "yes"
  }
},
{
  "type": "node",
  "id": 6258483260,
  "lat": 49.6360223,
  "lon": -1.6433517,
  "tags": {
    "bench": "yes",
    "bin": "yes",
    "bus": "yes",
    "departures_board": "timetable",
    "highway": "bus_stop",
    "name": "Université",
    "network": "Cap Cotentin",
    "operator": "Communauté d'agglomération du Cotentin",
    "public_transport": "platform",
    "ref": "Université",
    "route_ref": "1",
    "shelter": "yes",
    "type": "public_transport",
    "wheelchair": "yes"
  }
},
{
  "type": "node",
  "id": 6258489040,
  "lat": 49.6357693,
  "lon": -1.6434734,
  "tags": {
    "bench": "yes",
    "bin": "yes",
    "bus": "yes",
    "departures_board": "yes",
    "highway": "bus_stop",
    "name": "Université",
    "network": "Cap Cotentin",
    "operator": "Communauté d'agglomération du Cotentin",
    "public_transport": "platform",
    "ref": "Université",
    "route_ref": "1",
    "shelter": "yes",
    "type": "public_transport",
    "wheelchair": "yes"
  }
},
{
  "type": "node",
  "id": 6258497398,
  "lat": 49.6352769,
  "lon": -1.6460801,
  "tags": {
    "bench": "yes",
    "bin": "yes",
    "bus": "yes",
    "departures_board": "timetable",
    "highway": "bus_stop",
    "name": "IUT",
    "network": "Cap Cotentin",
    "operator": "Communauté d'agglomération du Cotentin",
    "public_transport": "platform",
    "ref": "IUT",
    "route_ref": "1",
    "shelter": "yes",
    "type": "public_transport",
    "wheelchair": "yes"
  }
},
{
  "type": "node",
  "id": 6258497399,
  "lat": 49.6352580,
  "lon": -1.6459141,
  "tags": {
    "bench": "yes",
    "bin": "yes",
    "bus": "yes",
    "departures_board": "timetable",
    "highway": "bus_stop",
    "name": "IUT",
    "network": "Cap Cotentin",
    "operator": "Communauté d'agglomération du Cotentin",
    "public_transport": "platform",
    "ref": "IUT",
    "route_ref": "1;d",
    "shelter": "yes",
    "type": "public_transport",
    "wheelchair": "yes"
  }
},
{
  "type": "node",
  "id": 6259119082,
  "lat": 49.6402350,
  "lon": -1.6427685,
  "tags": {
    "bus": "yes",
    "highway": "bus_stop",
    "name": "Millet",
    "network": "Zéphir Bus",
    "operator": "Keolis",
    "public_transport": "platform",
    "ref": "Millet"
  }
},
{
  "type": "node",
  "id": 6259130911,
  "lat": 49.6399277,
  "lon": -1.6397506,
  "tags": {
    "bus": "yes",
    "highway": "bus_stop",
    "name": "Le Conquérant",
    "public_transport": "platform",
    "route_ref": "1;4"
  }
},
{
  "type": "node",
  "id": 6259157506,
  "lat": 49.6295729,
  "lon": -1.6404179,
  "tags": {
    "bus": "yes",
    "highway": "bus_stop",
    "name": "Sadi Carnot",
    "network": "Zéphir Bus",
    "operator": "Keolis",
    "public_transport": "platform",
    "ref": "Sadi Carnot",
    "route_ref": "2"
  }
},
{
  "type": "node",
  "id": 6259157507,
  "lat": 49.6295152,
  "lon": -1.6406526,
  "tags": {
    "bus": "yes",
    "departures_board": "timetable",
    "highway": "bus_stop",
    "name": "Sadi Carnot",
    "network": "Cap Cotentin",
    "operator": "Keolis",
    "public_transport": "platform",
    "ref": "Sadi Carnot",
    "route_ref": "2",
    "shelter": "no",
    "wheelchair": "no"
  }
},
{
  "type": "node",
  "id": 6259194155,
  "lat": 49.6272815,
  "lon": -1.6353148,
  "tags": {
    "bench": "yes",
    "bus": "yes",
    "highway": "bus_stop",
    "name": "Anjou",
    "network": "Zéphir Bus",
    "operator": "Keolis",
    "public_transport": "platform",
    "route_ref": "1",
    "shelter": "yes"
  }
},
{
  "type": "node",
  "id": 6259194156,
  "lat": 49.6267855,
  "lon": -1.6347301,
  "tags": {
    "bench": "no",
    "bus": "yes",
    "highway": "bus_stop",
    "name": "Anjou",
    "network": "Zéphir Bus",
    "operator": "Keolis",
    "public_transport": "platform",
    "ref": "Anjou",
    "route_ref": "8",
    "shelter": "no"
  }
},
{
  "type": "node",
  "id": 6259332782,
  "lat": 49.6273914,
  "lon": -1.6256494,
  "tags": {
    "bench": "yes",
    "bus": "yes",
    "highway": "bus_stop",
    "name": "Église",
    "network": "Zéphir Bus",
    "operator": "Keolis",
    "public_transport": "platform",
    "ref": "Église",
    "route_ref": "1;8",
    "shelter": "yes"
  }
},
{
  "type": "node",
  "id": 6259333366,
  "lat": 49.6273812,
  "lon": -1.6254148,
  "tags": {
    "bench": "yes",
    "bus": "yes",
    "highway": "bus_stop",
    "name": "Église",
    "network": "Zéphir Bus",
    "operator": "Keolis",
    "public_transport": "platform",
    "ref": "Église",
    "route_ref": "1;8",
    "shelter": "yes"
  }
},
{
  "type": "node",
  "id": 6259341278,
  "lat": 49.6294349,
  "lon": -1.6230115,
  "tags": {
    "bench": "yes",
    "bus": "yes",
    "highway": "bus_stop",
    "name": "Amont Quentin",
    "network": "Zéphir Bus",
    "operator": "Communauté d'agglomération du Cotentin",
    "public_transport": "platform",
    "ref": "Amont Quentin",
    "route_ref": "1;8",
    "shelter": "yes",
    "tactile_paving": "yes",
    "wheelchair": "yes"
  }
},
{
  "type": "node",
  "id": 6259341279,
  "lat": 49.6293460,
  "lon": -1.6232504,
  "tags": {
    "bench": "yes",
    "bus": "yes",
    "highway": "bus_stop",
    "name": "Amont Quentin",
    "network": "Zéphir Bus",
    "operator": "Communauté d'agglomération du Cotentin",
    "public_transport": "platform",
    "route_ref": "1;8",
    "shelter": "yes",
    "tactile_paving": "yes",
    "wheelchair": "yes"
  }
},
{
  "type": "node",
  "id": 6259591557,
  "lat": 49.6245734,
  "lon": -1.6485230,
  "tags": {
    "bus": "yes",
    "departures_board": "timetable",
    "highway": "bus_stop",
    "name": "Coteaux",
    "network": "Cap Cotentin",
    "operator": "Communauté d'agglomération du Cotentin",
    "public_transport": "platform",
    "route_ref": "2",
    "shelter": "no",
    "type": "public_transport",
    "wheelchair": "yes"
  }
},
{
  "type": "node",
  "id": 6259610470,
  "lat": 49.6224896,
  "lon": -1.6523749,
  "tags": {
    "bench": "no",
    "bin": "no",
    "bus": "yes",
    "highway": "bus_stop",
    "mapillary": "179418787413983",
    "name": "Beauchamp",
    "network": "Zéphir Bus",
    "operator": "Keolis",
    "public_transport": "platform",
    "route_ref": "2",
    "shelter": "no",
    "survey:date": "2020-07-25"
  }
},
{
  "type": "node",
  "id": 6259610471,
  "lat": 49.6229405,
  "lon": -1.6520840,
  "tags": {
    "bench": "no",
    "bin": "no",
    "bus": "yes",
    "highway": "bus_stop",
    "mapillary": "930322837512452",
    "name": "Beauchamp",
    "network": "Zéphir Bus",
    "operator": "Keolis",
    "public_transport": "platform",
    "route_ref": "2",
    "shelter": "no",
    "survey:date": "2020-07-25"
  }
},
{
  "type": "node",
  "id": 6259619397,
  "lat": 49.6209412,
  "lon": -1.6561322,
  "tags": {
    "bench": "no",
    "bin": "no",
    "bus": "yes",
    "departures_board": "timetable",
    "highway": "bus_stop",
    "mapillary": "175989140985215",
    "name": "Chemin des Fossés",
    "public_transport": "platform",
    "route_ref": "2",
    "shelter": "no",
    "survey:date": "2020-07-25",
    "type": "public_transport",
    "wheelchair": "yes"
  }
},
{
  "type": "node",
  "id": 6259619398,
  "lat": 49.6209401,
  "lon": -1.6559045,
  "tags": {
    "bench": "no",
    "bin": "no",
    "bus": "yes",
    "departures_board": "timetable",
    "highway": "bus_stop",
    "mapillary": "306398241079106",
    "name": "Chemin des Fossés",
    "public_transport": "platform",
    "route_ref": "2",
    "shelter": "no",
    "survey:date": "2020-07-25",
    "type": "public_transport",
    "wheelchair": "yes"
  }
},
{
  "type": "node",
  "id": 6259635304,
  "lat": 49.6214887,
  "lon": -1.6608044,
  "tags": {
    "bus": "yes",
    "highway": "bus_stop",
    "name": "Digard",
    "public_transport": "platform",
    "route_ref": "2",
    "shelter": "yes",
    "wheelchair": "yes"
  }
},
{
  "type": "node",
  "id": 6259713666,
  "lat": 49.6288470,
  "lon": -1.6561478,
  "tags": {
    "bus": "yes",
    "departures_board": "timetable",
    "highway": "bus_stop",
    "name": "Grimesnil",
    "network": "Cap Cotentin",
    "operator": "Communauté d'agglomération du Cotentin",
    "public_transport": "platform",
    "route_ref": "8;d",
    "type": "public_transport",
    "wheelchair": "yes"
  }
},
{
  "type": "node",
  "id": 6259713667,
  "lat": 49.6288601,
  "lon": -1.6559997,
  "tags": {
    "bus": "yes",
    "departures_board": "timetable",
    "highway": "bus_stop",
    "name": "Grimesnil",
    "network": "Zéphir Bus",
    "operator": "Keolis",
    "public_transport": "platform",
    "route_ref": "8",
    "type": "public_transport",
    "wheelchair": "yes"
  }
},
{
  "type": "node",
  "id": 6259726814,
  "lat": 49.6280164,
  "lon": -1.6537845,
  "tags": {
    "bus": "yes",
    "departures_board": "timetable",
    "highway": "bus_stop",
    "name": "Fouëdre",
    "network": "Cap Cotentin",
    "operator": "Communauté d'agglomération du Cotentin",
    "public_transport": "platform",
    "route_ref": "8;d"
  }
},
{
  "type": "node",
  "id": 6259728128,
  "lat": 49.6281005,
  "lon": -1.6538315,
  "tags": {
    "bus": "yes",
    "departures_board": "timetable",
    "highway": "bus_stop",
    "name": "Fouëdre",
    "network": "Cap Cotentin",
    "operator": "Communauté d'agglomération du Cotentin",
    "public_transport": "platform",
    "route_ref": "8",
    "type": "public_transport",
    "wheelchair": "yes"
  }
},
{
  "type": "node",
  "id": 6259744402,
  "lat": 49.6286511,
  "lon": -1.6488359,
  "tags": {
    "bus": "yes",
    "departures_board": "timetable",
    "highway": "bus_stop",
    "name": "Maison de Retraite",
    "network": "Cap Cotentin",
    "operator": "Communauté d'agglomération du Cotentin",
    "public_transport": "platform",
    "route_ref": "8",
    "wheelchair": "yes"
  }
},
{
  "type": "node",
  "id": 6259744403,
  "lat": 49.6286360,
  "lon": -1.6485875,
  "tags": {
    "bench": "yes",
    "bin": "yes",
    "bus": "yes",
    "departures_board": "timetable",
    "highway": "bus_stop",
    "name": "Maison de Retraite",
    "network": "Capital Bikeshare",
    "operator": "Communauté d'agglomération du Cotentin",
    "public_transport": "platform",
    "route_ref": "8",
    "shelter": "yes",
    "type": "public_transport",
    "wheelchair": "yes"
  }
},
{
  "type": "node",
  "id": 6259794252,
  "lat": 49.6316670,
  "lon": -1.6385516,
  "tags": {
    "bench": "no",
    "bin": "no",
    "bus": "yes",
    "highway": "bus_stop",
    "mapillary": "1241550556292119",
    "name": "Voltaire",
    "network": "Zéphir Bus",
    "operator": "Keolis",
    "public_transport": "platform",
    "route_ref": "2",
    "shelter": "no",
    "survey:date": "2020-07-25"
  }
},
{
  "type": "node",
  "id": 6259822875,
  "lat": 49.6365598,
  "lon": -1.6343093,
  "tags": {
    "bench": "no",
    "bus": "yes",
    "highway": "bus_stop",
    "name": "F.J.T.",
    "network": "Zéphir Bus",
    "operator": "Keolis",
    "public_transport": "platform",
    "route_ref": "2",
    "shelter": "no",
    "tactile_paving": "yes"
  }
},
{
  "type": "node",
  "id": 6259822876,
  "lat": 49.6366404,
  "lon": -1.6342658,
  "tags": {
    "bench": "no",
    "bus": "yes",
    "highway": "bus_stop",
    "name": "F.J.T.",
    "network": "Zéphir Bus",
    "operator": "Keolis",
    "public_transport": "platform",
    "route_ref": "2",
    "shelter": "no",
    "tactile_paving": "yes"
  }
},
{
  "type": "node",
  "id": 6260084124,
  "lat": 49.6414455,
  "lon": -1.6603195,
  "tags": {
    "bus": "yes",
    "highway": "bus_stop",
    "name": "Le Tôt",
    "network": "Itinéo",
    "operator": "Keolis",
    "public_transport": "platform"
  }
},
{
  "type": "node",
  "id": 6260085912,
  "lat": 49.6435974,
  "lon": -1.6582346,
  "tags": {
    "bus": "yes",
    "highway": "bus_stop",
    "name": "Vieux Tôt",
    "network": "Zéphir Bus",
    "operator": "Communauté d'agglomération du Cotentin",
    "public_transport": "platform"
  }
},
{
  "type": "node",
  "id": 6260085913,
  "lat": 49.6437445,
  "lon": -1.6579491,
  "tags": {
    "bus": "yes",
    "highway": "bus_stop",
    "name": "Vieux Tôt",
    "public_transport": "platform"
  }
},
{
  "type": "node",
  "id": 7362919483,
  "lat": 49.6327690,
  "lon": -1.6453311,
  "tags": {
    "bus": "yes",
    "highway": "bus_stop",
    "public_transport": "platform"
  }
},
{
  "type": "node",
  "id": 7474172283,
  "lat": 49.6319307,
  "lon": -1.6175249,
  "tags": {
    "bus": "yes",
    "departures_board": "timetable",
    "highway": "bus_stop",
    "name": "Jardin Public",
    "network": "Zéphir Bus",
    "operator": "Aglo du Cotenin",
    "public_transport": "platform",
    "shelter": "yes"
  }
},
{
  "type": "node",
  "id": 7489112440,
  "lat": 49.6343992,
  "lon": -1.5668949,
  "tags": {
    "bus": "yes",
    "departures_board": "yes",
    "highway": "bus_stop",
    "name": "Églantine Château",
    "network": "Zéphir Bus",
    "operator": "Communauté d'agglomération du Cotentin",
    "public_transport": "platform",
    "shelter": "yes",
    "wheelchair": "yes"
  }
},
{
  "type": "node",
  "id": 7489658027,
  "lat": 49.6357570,
  "lon": -1.6246921,
  "tags": {
    "bus": "yes",
    "departures_board": "realtime",
    "highway": "bus_stop",
    "name": "Schuman",
    "network": "Cap Cotentin",
    "operator": "Communauté d'agglomération du Cotentin",
    "public_transport": "platform",
    "shelter": "yes",
    "wheelchair": "yes"
  }
},
{
  "type": "node",
  "id": 7490256964,
  "lat": 49.6325202,
  "lon": -1.5981058,
  "tags": {
    "bus": "yes",
    "highway": "bus_stop",
    "name": "Fleming",
    "network": "Zéphir Bus",
    "operator": "Communauté d'agglomération du Cotentin",
    "public_transport": "platform",
    "shelter": "no",
    "wheelchair": "yes"
  }
},
{
  "type": "node",
  "id": 7490256965,
  "lat": 49.6320331,
  "lon": -1.5976982,
  "tags": {
    "bus": "yes",
    "highway": "bus_stop",
    "name": "Fleming",
    "network": "Zéphir Bus",
    "operator": "Communauté d'agglomération du Cotentin",
    "public_transport": "platform",
    "shelter": "no",
    "wheelchair": "yes"
  }
},
{
  "type": "node",
  "id": 7494970921,
  "lat": 49.6597524,
  "lon": -1.7152390,
  "tags": {
    "bus": "yes",
    "highway": "bus_stop",
    "name": "Amfreville",
    "public_transport": "platform",
    "wheelchair": "no"
  }
},
{
  "type": "node",
  "id": 7501558465,
  "lat": 49.6507357,
  "lon": -1.5834264,
  "tags": {
    "bus": "yes",
    "highway": "bus_stop",
    "name": "Flamands",
    "network": "Zéphir Bus",
    "operator": "Communauté d'agglomération du Cotentin",
    "public_transport": "platform",
    "shelter": "yes",
    "wheelchair": "yes"
  }
},
{
  "type": "node",
  "id": 7501757520,
  "lat": 49.6530853,
  "lon": -1.5513126,
  "tags": {
    "bus": "yes",
    "highway": "bus_stop",
    "name": "Becquet",
    "network": "Zéphir Bus",
    "operator": "Communauté d'agglomération du Cotentin",
    "public_transport": "platform",
    "shelter": "yes",
    "wheelchair": "yes"
  }
},
{
  "type": "node",
  "id": 7501757521,
  "lat": 49.6530029,
  "lon": -1.5512560,
  "tags": {
    "bus": "yes",
    "highway": "bus_stop",
    "name": "Becquet",
    "network": "Zéphir Bus",
    "operator": "Communauté d'agglomération du Cotentin",
    "public_transport": "platform",
    "shelter": "no",
    "wheelchair": "yes"
  }
},
{
  "type": "node",
  "id": 7504246855,
  "lat": 49.6253404,
  "lon": -1.5870633,
  "tags": {
    "bus": "yes",
    "highway": "bus_stop",
    "name": "Hameau Quévillon",
    "network": "Zéphir Bus",
    "operator": "Communauté d'agglomération du Cotentin",
    "public_transport": "platform",
    "shelter": "yes",
    "wheelchair": "yes"
  }
},
{
  "type": "node",
  "id": 7504246857,
  "lat": 49.6252313,
  "lon": -1.5871588,
  "tags": {
    "bus": "yes",
    "highway": "bus_stop",
    "name": "Hameau Quévillon",
    "network": "Zéphir Bus",
    "operator": "Communauté d'agglomération du Cotentin",
    "public_transport": "platform",
    "shelter": "no",
    "wheelchair": "limited"
  }
},
{
  "type": "node",
  "id": 7515713822,
  "lat": 49.6212037,
  "lon": -1.5784903,
  "tags": {
    "bus": "yes",
    "highway": "bus_stop",
    "name": "Hameau Quévastre",
    "network": "Zéphir Bus",
    "operator": "Communauté d'agglomération du Cotentin",
    "public_transport": "platform",
    "shelter": "no",
    "wheelchair": "no"
  }
},
{
  "type": "node",
  "id": 7515713823,
  "lat": 49.6212513,
  "lon": -1.5781494,
  "tags": {
    "bus": "yes",
    "highway": "bus_stop",
    "name": "Hameau Quévastre",
    "network": "Zéphir Bus",
    "operator": "Communauté d'agglomération du Cotentin",
    "public_transport": "platform",
    "shelter": "no",
    "wheelchair": "no"
  }
},
{
  "type": "node",
  "id": 7515717046,
  "lat": 49.6339737,
  "lon": -1.6215405,
  "tags": {
    "bus": "yes",
    "departures_board": "realtime",
    "highway": "bus_stop",
    "name": "Gare SNCF",
    "public_transport": "platform",
    "shelter": "yes",
    "wheelchair": "yes"
  }
},
{
  "type": "node",
  "id": 7515717055,
  "lat": 49.6369907,
  "lon": -1.6255155,
  "tags": {
    "bus": "yes",
    "departures_board": "realtime",
    "highway": "bus_stop",
    "name": "Schuman",
    "network": "Zéphir Bus",
    "operator": "Communauté d'agglomération du Cotentin",
    "public_transport": "platform",
    "shelter": "yes",
    "wheelchair": "yes"
  }
},
{
  "type": "node",
  "id": 7519317818,
  "lat": 49.6665932,
  "lon": -1.7009972,
  "tags": {
    "bus": "yes",
    "highway": "bus_stop",
    "name": "La Marche",
    "network": "Zéphir Bus",
    "operator": "Communauté d'agglomération du Cotentin",
    "public_transport": "platform",
    "shelter": "yes",
    "wheelchair": "yes"
  }
},
{
  "type": "node",
  "id": 7519317824,
  "lat": 49.6666328,
  "lon": -1.7032715,
  "tags": {
    "bus": "yes",
    "highway": "bus_stop",
    "name": "Cité des Bruyères",
    "network": "Zéphir Bus",
    "operator": "Communauté d'agglomération du Cotentin",
    "public_transport": "platform",
    "shelter": "no",
    "wheelchair": "yes"
  }
},
{
  "type": "node",
  "id": 7519317825,
  "lat": 49.6657787,
  "lon": -1.7016380,
  "tags": {
    "bus": "yes",
    "highway": "bus_stop",
    "name": "Pierre Cardon",
    "network": "Zéphir Bus",
    "operator": "Communauté d'agglomération du Cotentin",
    "public_transport": "platform",
    "shelter": "no",
    "wheelchair": "no"
  }
},
{
  "type": "node",
  "id": 7519317826,
  "lat": 49.6660492,
  "lon": -1.6984877,
  "tags": {
    "bus": "yes",
    "highway": "bus_stop",
    "name": "La Mer",
    "network": "Zéphir Bus",
    "operator": "Communauté d'agglomération du Cotentin",
    "public_transport": "platform",
    "shelter": "no",
    "wheelchair": "limited"
  }
},
{
  "type": "node",
  "id": 7519317838,
  "lat": 49.6639292,
  "lon": -1.6997330,
  "tags": {
    "bus": "yes",
    "highway": "bus_stop",
    "name": "Mont Faucon",
    "network": "Zéphir Bus",
    "operator": "Communauté d'agglomération du Cotentin",
    "public_transport": "platform",
    "shelter": "no",
    "wheelchair": "limited"
  }
},
{
  "type": "node",
  "id": 7519317839,
  "lat": 49.6649598,
  "lon": -1.6966981,
  "tags": {
    "bus": "yes",
    "highway": "bus_stop",
    "name": "Roger Glinel",
    "network": "Zéphir Bus",
    "operator": "Communauté d'agglomération du Cotentin",
    "public_transport": "platform",
    "shelter": "no",
    "wheelchair": "yes"
  }
},
{
  "type": "node",
  "id": 7519317840,
  "lat": 49.6649277,
  "lon": -1.6961283,
  "tags": {
    "bus": "yes",
    "highway": "bus_stop",
    "name": "Roger Glinel",
    "network": "Zéphir Bus",
    "operator": "Communauté d'agglomération du Cotentin",
    "public_transport": "platform",
    "shelter": "no",
    "wheelchair": "yes"
  }
},
{
  "type": "node",
  "id": 7538715413,
  "lat": 49.6532605,
  "lon": -1.6769119,
  "tags": {
    "bus": "yes",
    "highway": "bus_stop",
    "name": "Hainneville Haut",
    "network": "Zéphir Bus",
    "operator": "Communauté d'agglomération du Cotentin",
    "public_transport": "platform",
    "shelter": "no",
    "wheelchair": "limited"
  }
},
{
  "type": "node",
  "id": 7538715414,
  "lat": 49.6531163,
  "lon": -1.6770567,
  "tags": {
    "bus": "yes",
    "highway": "bus_stop",
    "name": "Hainneville Haut",
    "network": "Zéphir Bus",
    "operator": "Communauté d'agglomération du Cotentin",
    "public_transport": "platform",
    "shelter": "no",
    "wheelchair": "limited"
  }
},
{
  "type": "node",
  "id": 7538715477,
  "lat": 49.6497223,
  "lon": -1.6506032,
  "tags": {
    "bus": "yes",
    "departures_board": "realtime",
    "highway": "bus_stop",
    "name": "Terrasses",
    "network": "Zéphir Bus",
    "operator": "Communauté d'agglomération du Cotentin",
    "public_transport": "platform",
    "shelter": "yes",
    "wheelchair": "yes"
  }
},
{
  "type": "node",
  "id": 7541959108,
  "lat": 49.6357799,
  "lon": -1.5787252,
  "tags": {
    "bus": "yes",
    "highway": "bus_stop",
    "name": "ZAC Sauxmarais",
    "network": "Cap Cotentin",
    "network:wikidata": "Q3576504",
    "network:wikipedia": "fr:Transports en commun de Cherbourg-en-Cotentin",
    "operator": "Keolis Cherbourg",
    "public_transport": "platform",
    "wheelchair": "limited"
  }
},
{
  "type": "node",
  "id": 7552406433,
  "lat": 49.6318622,
  "lon": -1.6104358,
  "tags": {
    "departures_board": "timetable",
    "highway": "bus_stop",
    "name": "Lecarpentier",
    "network": "Ligne 5",
    "operator": "Zephir Bus",
    "public_transport": "platform",
    "shelter": "yes"
  }
},
{
  "type": "node",
  "id": 7552406434,
  "lat": 49.6317232,
  "lon": -1.6103178,
  "tags": {
    "bus": "yes",
    "departures_board": "timetable",
    "highway": "bus_stop",
    "name": "Lecarpentier",
    "network": "Ligne 5",
    "operator": "Zephir Bus",
    "public_transport": "platform",
    "shelter": "no"
  }
},
{
  "type": "node",
  "id": 7556974898,
  "lat": 49.6389460,
  "lon": -1.6066381,
  "tags": {
    "bus": "yes",
    "departures_board": "timetable",
    "highway": "bus_stop",
    "name": "Octroi",
    "network": "Zéphir Bus",
    "operator": "Communauté d'agglomération du Cotentin",
    "public_transport": "platform",
    "shelter": "yes",
    "wheelchair": "yes"
  }
},
{
  "type": "node",
  "id": 7556974899,
  "lat": 49.6391106,
  "lon": -1.6060927,
  "tags": {
    "bus": "yes",
    "highway": "bus_stop",
    "name": "Octroi",
    "network": "Zéphir Bus",
    "operator": "Communauté d'agglomération du Cotentin",
    "public_transport": "platform",
    "shelter": "no",
    "wheelchair": "yes"
  }
},
{
  "type": "node",
  "id": 7559746147,
  "lat": 49.6087034,
  "lon": -1.6007450,
  "tags": {
    "bench": "yes",
    "bus": "yes",
    "departures_board": "timetable",
    "highway": "bus_stop",
    "name": "Debussy",
    "public_transport": "platform",
    "shelter": "yes",
    "wheelchair": "yes"
  }
},
{
  "type": "node",
  "id": 7559746149,
  "lat": 49.6086715,
  "lon": -1.6015757,
  "tags": {
    "bench": "no",
    "bin": "no",
    "bus": "yes",
    "departures_board": "timetable",
    "highway": "bus_stop",
    "name": "Debussy",
    "public_transport": "platform",
    "shelter": "no",
    "wheelchair": "yes"
  }
},
{
  "type": "node",
  "id": 7563814669,
  "lat": 49.6336728,
  "lon": -1.6225198,
  "tags": {
    "bus": "yes",
    "departures_board": "realtime",
    "highway": "bus_stop",
    "name": "Jean Jaurès",
    "network": "Zéphir Bus",
    "operator": "Communauté d'agglomération du Cotentin",
    "public_transport": "platform",
    "shelter": "yes",
    "wheelchair": "yes"
  }
},
{
  "type": "node",
  "id": 7563818623,
  "lat": 49.6435188,
  "lon": -1.6649269,
  "tags": {
    "bus": "yes",
    "highway": "bus_stop",
    "name": "Les Lavandes",
    "network": "Zéphir Bus",
    "operator": "Communauté d'agglomération du Cotentin",
    "public_transport": "platform"
  }
},
{
  "type": "node",
  "id": 7564282698,
  "lat": 49.6573765,
  "lon": -1.7056038,
  "tags": {
    "bus": "yes",
    "highway": "bus_stop",
    "name": "Les Mourets",
    "public_transport": "platform",
    "shelter": "no",
    "wheelchair": "yes"
  }
},
{
  "type": "node",
  "id": 7566262614,
  "lat": 49.6407222,
  "lon": -1.5963244,
  "tags": {
    "bus": "yes",
    "departures_board": "timetable",
    "highway": "bus_stop",
    "name": "Bagatelle",
    "network": "Zéphir Bus",
    "operator": "Communauté d'agglomération du Cotentin",
    "public_transport": "platform",
    "shelter": "no",
    "wheelchair": "yes"
  }
},
{
  "type": "node",
  "id": 7566262618,
  "lat": 49.6309935,
  "lon": -1.6043643,
  "tags": {
    "bus": "yes",
    "departures_board": "timetable",
    "highway": "bus_stop",
    "name": "Bremerhaven Haut",
    "network": "Ligne 5",
    "operator": "Zephir",
    "public_transport": "platform",
    "shelter": "yes"
  }
},
{
  "type": "node",
  "id": 7566262619,
  "lat": 49.6310413,
  "lon": -1.6039382,
  "tags": {
    "bus": "yes",
    "departures_board": "timetable",
    "highway": "bus_stop",
    "name": "Bremerhaven Haut",
    "network": "Ligne 5",
    "operator": "Zephir Bus",
    "public_transport": "platform",
    "shelter": "no"
  }
},
{
  "type": "node",
  "id": 7566262620,
  "lat": 49.6308093,
  "lon": -1.6055649,
  "tags": {
    "bus": "yes",
    "departures_board": "timetable",
    "highway": "bus_stop",
    "name": "Bremerhaven Centre",
    "public_transport": "platform",
    "route_ref": "Ligne 5",
    "shelter": "yes"
  }
},
{
  "type": "node",
  "id": 7566262621,
  "lat": 49.6311886,
  "lon": -1.6070827,
  "tags": {
    "bus": "yes",
    "departures_board": "timetable",
    "highway": "bus_stop",
    "name": "Bremerhaven Centre",
    "network": "Ligne 5",
    "operator": "Zephir Bus",
    "public_transport": "platform",
    "shelter": "yes"
  }
},
{
  "type": "node",
  "id": 7566291398,
  "lat": 49.6408182,
  "lon": -1.5962773,
  "tags": {
    "bus": "yes",
    "departures_board": "timetable",
    "highway": "bus_stop",
    "name": "Bagatelle",
    "public_transport": "platform",
    "shelter": "no"
  }
},
{
  "type": "node",
  "id": 7566322465,
  "lat": 49.6346468,
  "lon": -1.6153491,
  "tags": {
    "bus": "yes",
    "departures_board": "timetable",
    "highway": "bus_stop",
    "name": "Themis Hopital",
    "public_transport": "platform",
    "shelter": "yes"
  }
},
{
  "type": "node",
  "id": 7566322466,
  "lat": 49.6345726,
  "lon": -1.6156213,
  "tags": {
    "bus": "yes",
    "departures_board": "timetable",
    "highway": "bus_stop",
    "name": "Themis Hopital",
    "public_transport": "platform",
    "shelter": "yes"
  }
},
{
  "type": "node",
  "id": 7566322467,
  "lat": 49.6354209,
  "lon": -1.6171191,
  "tags": {
    "bus": "yes",
    "departures_board": "timetable",
    "highway": "bus_stop",
    "name": "Eleis Jacques Hebert",
    "network": "Ligne 3",
    "operator": "Zephir Bus",
    "public_transport": "platform",
    "shelter": "yes"
  }
},
{
  "type": "node",
  "id": 7566362366,
  "lat": 49.6382217,
  "lon": -1.6166423,
  "tags": {
    "bus": "yes",
    "departures_board": "timetable",
    "highway": "bus_stop",
    "name": "Place Ravenel",
    "network": "Ligne 3",
    "operator": "Zephir Bus",
    "public_transport": "platform",
    "shelter": "yes"
  }
},
{
  "type": "node",
  "id": 7566362367,
  "lat": 49.6386131,
  "lon": -1.6131713,
  "tags": {
    "bus": "yes",
    "departures_board": "timetable",
    "highway": "bus_stop",
    "name": "Hopital Pasteur",
    "network": "Ligne 3",
    "operator": "Zephir Bus",
    "public_transport": "platform",
    "shelter": "yes"
  }
},
{
  "type": "node",
  "id": 7566362368,
  "lat": 49.6384370,
  "lon": -1.6119525,
  "tags": {
    "bus": "yes",
    "departures_board": "timetable",
    "highway": "bus_stop",
    "name": "Hopital Pasteur",
    "network": "Ligne3",
    "operator": "Zephir Bus",
    "public_transport": "platform",
    "shelter": "yes"
  }
},
{
  "type": "node",
  "id": 7566362369,
  "lat": 49.6417242,
  "lon": -1.5905006,
  "tags": {
    "bus": "yes",
    "departures_board": "timetable",
    "highway": "bus_stop",
    "name": "Mederic",
    "network": "Zephir Bus",
    "operator": "Communauté d'agglomération du Cotentin",
    "public_transport": "platform",
    "shelter": "no"
  }
},
{
  "type": "node",
  "id": 7566362370,
  "lat": 49.6419813,
  "lon": -1.5894456,
  "tags": {
    "bus": "yes",
    "departures_board": "timetable",
    "highway": "bus_stop",
    "name": "Mederic",
    "network": "Zephir Bus",
    "operator": "Communauté d'agglomération du Cotentin",
    "public_transport": "platform",
    "shelter": "no"
  }
},
{
  "type": "node",
  "id": 7566484882,
  "lat": 49.6444808,
  "lon": -1.5880382,
  "tags": {
    "bench": "no",
    "bin": "no",
    "bus": "yes",
    "departures_board": "timetable",
    "highway": "bus_stop",
    "name": "L'Îlot Z'Enfants",
    "network": "Cap Cotentin",
    "operator": "Communauté d'agglomération du Cotentin",
    "public_transport": "platform",
    "shelter": "no",
    "wheelchair": "yes"
  }
},
{
  "type": "node",
  "id": 7566484883,
  "lat": 49.6446222,
  "lon": -1.5877503,
  "tags": {
    "bench": "no",
    "bin": "no",
    "bus": "yes",
    "departures_board": "timetable",
    "highway": "bus_stop",
    "name": "L'Îlot Z'Enfants",
    "network": "Cap Cotentin",
    "operator": "Communauté d'agglomération du Cotentin",
    "public_transport": "platform",
    "shelter": "no",
    "wheelchair": "yes"
  }
},
{
  "type": "node",
  "id": 7566484884,
  "lat": 49.6466619,
  "lon": -1.5805456,
  "tags": {
    "bin": "no",
    "bus": "yes",
    "departures_board": "timetable",
    "highway": "bus_stop",
    "name": "Collège Diderot",
    "network": "Cap Cotentin",
    "operator": "Communauté d'agglomération du Cotentin",
    "public_transport": "platform",
    "shelter": "no",
    "wheelchair": "yes"
  }
},
{
  "type": "node",
  "id": 7566489785,
  "lat": 49.6472922,
  "lon": -1.5791117,
  "tags": {
    "bench": "no",
    "bin": "no",
    "bus": "yes",
    "departures_board": "timetable",
    "highway": "bus_stop",
    "name": "Collège Diderot",
    "network": "Cap Cotentin",
    "operator": "Communauté d'agglomération du Cotentin",
    "public_transport": "platform",
    "shelter": "no",
    "wheelchair": "yes"
  }
},
{
  "type": "node",
  "id": 7566489819,
  "lat": 49.6336047,
  "lon": -1.5919991,
  "tags": {
    "bus": "yes",
    "highway": "bus_stop",
    "name": "Brossolette",
    "network": "Zephir Bus",
    "operator": "Communauté d'aglo du cotentin",
    "public_transport": "platform",
    "shelter": "yes"
  }
},
{
  "type": "node",
  "id": 7566489820,
  "lat": 49.6332658,
  "lon": -1.5920798,
  "tags": {
    "bus": "yes",
    "highway": "bus_stop",
    "name": "Brossolette",
    "network": "Zephir Bus",
    "operator": "Communauté d'aglo du cotentin",
    "public_transport": "platform",
    "shelter": "yes"
  }
},
{
  "type": "node",
  "id": 7566941504,
  "lat": 49.6335249,
  "lon": -1.6206464,
  "tags": {
    "bench": "yes",
    "bus": "yes",
    "highway": "bus_stop",
    "name": "Gare SNCF",
    "public_transport": "platform",
    "shelter": "yes",
    "tactile_paving": "yes"
  }
},
{
  "type": "node",
  "id": 7569437305,
  "lat": 49.6033365,
  "lon": -1.6024805,
  "tags": {
    "bus": "yes",
    "departures_board": "timetable",
    "highway": "bus_stop",
    "name": "Centre Commercial",
    "public_transport": "platform",
    "shelter": "yes"
  }
},
{
  "type": "node",
  "id": 7569437306,
  "lat": 49.6037148,
  "lon": -1.6029798,
  "tags": {
    "bus": "yes",
    "departures_board": "timetable",
    "highway": "bus_stop",
    "name": "Centre Commercial",
    "network": "Zephir Bus",
    "operator": "Aglo Cotentin",
    "public_transport": "platform",
    "shelter": "no"
  }
},
{
  "type": "node",
  "id": 7569451338,
  "lat": 49.6424406,
  "lon": -1.6111626,
  "tags": {
    "bench": "no",
    "bus": "yes",
    "departures_board": "timetable",
    "highway": "bus_stop",
    "name": "CCI Multiplex",
    "network": "Zephir Bus",
    "operator": "Agglo du cotentin",
    "public_transport": "platform",
    "shelter": "no",
    "tactile_paving": "yes"
  }
},
{
  "type": "node",
  "id": 7569451339,
  "lat": 49.6425200,
  "lon": -1.6113531,
  "tags": {
    "bench": "no",
    "bus": "yes",
    "departures_board": "timetable",
    "highway": "bus_stop",
    "name": "CCI Multiplex",
    "network": "Zephir Bus",
    "operator": "Agglo du Cotentin",
    "public_transport": "platform",
    "shelter": "no",
    "tactile_paving": "yes"
  }
},
{
  "type": "node",
  "id": 7575490785,
  "lat": 49.6425748,
  "lon": -1.6159836,
  "tags": {
    "bus": "yes",
    "highway": "bus_stop",
    "public_transport": "platform"
  }
},
{
  "type": "node",
  "id": 7602124853,
  "lat": 49.6079962,
  "lon": -1.6072188,
  "tags": {
    "bench": "no",
    "bin": "no",
    "bus": "yes",
    "highway": "bus_stop",
    "name": "Curie",
    "public_transport": "platform",
    "shelter": "no"
  }
},
{
  "type": "node",
  "id": 7602124854,
  "lat": 49.6079684,
  "lon": -1.6068830,
  "tags": {
    "bench": "yes",
    "bus": "yes",
    "departures_board": "timetable",
    "highway": "bus_stop",
    "name": "Curie",
    "public_transport": "platform",
    "shelter": "yes"
  }
},
{
  "type": "node",
  "id": 7602124855,
  "lat": 49.6127057,
  "lon": -1.6002851,
  "tags": {
    "bench": "no",
    "bin": "no",
    "bus": "yes",
    "departures_board": "timetable",
    "highway": "bus_stop",
    "name": "Chapelle St Michel",
    "public_transport": "platform",
    "shelter": "no",
    "tactile_paving": "yes"
  }
},
{
  "type": "node",
  "id": 7602124856,
  "lat": 49.6126563,
  "lon": -1.6002032,
  "tags": {
    "bench": "yes",
    "bin": "no",
    "bus": "yes",
    "departures_board": "timetable",
    "highway": "bus_stop",
    "name": "Chapelle St Michel",
    "public_transport": "platform",
    "shelter": "yes"
  }
},
{
  "type": "node",
  "id": 7602124857,
  "lat": 49.6152757,
  "lon": -1.5964435,
  "tags": {
    "bench": "no",
    "bin": "no",
    "bus": "yes",
    "departures_board": "timetable",
    "highway": "bus_stop",
    "name": "Schweitzer",
    "public_transport": "platform",
    "shelter": "no"
  }
},
{
  "type": "node",
  "id": 7602124858,
  "lat": 49.6163316,
  "lon": -1.5965371,
  "tags": {
    "bench": "no",
    "bin": "no",
    "bus": "yes",
    "departures_board": "timetable",
    "highway": "bus_stop",
    "name": "Schweitzer",
    "public_transport": "platform",
    "shelter": "no",
    "tactile_paving": "yes"
  }
},
{
  "type": "node",
  "id": 7602124859,
  "lat": 49.6161683,
  "lon": -1.5987760,
  "tags": {
    "bench": "yes",
    "bin": "no",
    "bus": "yes",
    "highway": "bus_stop",
    "lit": "yes",
    "name": "Normandie",
    "public_transport": "platform",
    "shelter": "yes",
    "tactile_paving": "no"
  }
},
{
  "type": "node",
  "id": 7602124860,
  "lat": 49.6159829,
  "lon": -1.5988968,
  "tags": {
    "bench": "no",
    "bin": "no",
    "bus": "yes",
    "departures_board": "timetable",
    "highway": "bus_stop",
    "lit": "yes",
    "name": "Normandie",
    "public_transport": "platform",
    "shelter": "no",
    "tactile_paving": "no"
  }
},
{
  "type": "node",
  "id": 7602124861,
  "lat": 49.6161864,
  "lon": -1.6006637,
  "tags": {
    "bench": "no",
    "bin": "no",
    "bus": "yes",
    "departures_board": "timetable",
    "highway": "bus_stop",
    "name": "Blériot",
    "public_transport": "platform",
    "shelter": "no"
  }
},
{
  "type": "node",
  "id": 7602124862,
  "lat": 49.6160311,
  "lon": -1.6005887,
  "tags": {
    "bench": "no",
    "bin": "no",
    "bus": "yes",
    "departures_board": "timetable",
    "highway": "bus_stop",
    "lit": "yes",
    "name": "Blériot",
    "public_transport": "platform",
    "shelter": "no",
    "tactile_paving": "yes"
  }
},
{
  "type": "node",
  "id": 7602124863,
  "lat": 49.6160944,
  "lon": -1.6025515,
  "tags": {
    "bench": "yes",
    "bin": "no",
    "bus": "yes",
    "departures_board": "timetable",
    "highway": "bus_stop",
    "name": "H. Cornat",
    "public_transport": "platform",
    "shelter": "yes",
    "tactile_paving": "yes",
    "wheelchair": "yes"
  }
},
{
  "type": "node",
  "id": 7602124864,
  "lat": 49.6160444,
  "lon": -1.6051885,
  "tags": {
    "bus": "yes",
    "departures_board": "timetable",
    "highway": "bus_stop",
    "name": "Saint-Exupery",
    "public_transport": "platform",
    "shelter": "yes",
    "wheelchair": "limited"
  }
},
{
  "type": "node",
  "id": 7602124865,
  "lat": 49.6162086,
  "lon": -1.6055611,
  "tags": {
    "bus": "yes",
    "departures_board": "timetable",
    "highway": "bus_stop",
    "name": "Saint-Exupery",
    "public_transport": "platform",
    "shelter": "no"
  }
},
{
  "type": "node",
  "id": 7602124866,
  "lat": 49.6178808,
  "lon": -1.6071705,
  "tags": {
    "bus": "yes",
    "departures_board": "timetable",
    "highway": "bus_stop",
    "name": "Montmartre",
    "network": "Zephir Bus",
    "operator": "Aglo du Cotentin",
    "public_transport": "platform",
    "shelter": "no",
    "wheelchair": "limited"
  }
},
{
  "type": "node",
  "id": 7602124867,
  "lat": 49.6178040,
  "lon": -1.6071114,
  "tags": {
    "bench": "no",
    "bin": "no",
    "bus": "yes",
    "departures_board": "timetable",
    "highway": "bus_stop",
    "name": "Montmartre",
    "network": "Zephir Bus",
    "operator": "Aglo du Cotentin",
    "public_transport": "platform",
    "shelter": "no"
  }
},
{
  "type": "node",
  "id": 7602124868,
  "lat": 49.6220917,
  "lon": -1.6028183,
  "tags": {
    "bus": "yes",
    "departures_board": "timetable",
    "highway": "bus_stop",
    "name": "La Motterie",
    "network": "Zephir Bus",
    "operator": "Aglo du Cotentin",
    "public_transport": "platform",
    "shelter": "no"
  }
},
{
  "type": "node",
  "id": 7602124869,
  "lat": 49.6220956,
  "lon": -1.6029580,
  "tags": {
    "bus": "yes",
    "departures_board": "timetable",
    "highway": "bus_stop",
    "name": "La Motterie",
    "network": "Zephir Bus",
    "operator": "Aglo du Cotentin",
    "public_transport": "platform",
    "shelter": "no"
  }
},
{
  "type": "node",
  "id": 7602124870,
  "lat": 49.6195806,
  "lon": -1.5969065,
  "tags": {
    "bus": "yes",
    "departures_board": "timetable",
    "highway": "bus_stop",
    "name": "Gendarmerie",
    "network": "Zephir Bus",
    "operator": "Aglo du Cotentin",
    "public_transport": "platform",
    "shelter": "no"
  }
},
{
  "type": "node",
  "id": 7602124871,
  "lat": 49.6196309,
  "lon": -1.5966734,
  "tags": {
    "bus": "yes",
    "departures_board": "timetable",
    "highway": "bus_stop",
    "name": "Gendarmerie",
    "network": "Zephir Bus",
    "operator": "Aglo du Cotentin",
    "public_transport": "platform",
    "shelter": "no"
  }
},
{
  "type": "node",
  "id": 7602207793,
  "lat": 49.6189123,
  "lon": -1.6095815,
  "tags": {
    "bench": "yes",
    "bus": "yes",
    "departures_board": "timetable",
    "highway": "bus_stop",
    "name": "Beausejour",
    "public_transport": "platform",
    "shelter": "yes"
  }
},
{
  "type": "node",
  "id": 7602207794,
  "lat": 49.6187865,
  "lon": -1.6095510,
  "tags": {
    "bench": "no",
    "bus": "yes",
    "departures_board": "timetable",
    "highway": "bus_stop",
    "name": "Beausejour",
    "network": "Zephir Bus",
    "operator": "Aglo du Cotentin",
    "public_transport": "platform",
    "shelter": "no"
  }
},
{
  "type": "node",
  "id": 7602207795,
  "lat": 49.6200308,
  "lon": -1.6114265,
  "tags": {
    "bench": "yes",
    "bin": "no",
    "bus": "yes",
    "departures_board": "timetable",
    "highway": "bus_stop",
    "lit": "yes",
    "name": "La Ruche",
    "public_transport": "platform",
    "shelter": "yes",
    "tactile_paving": "yes"
  }
},
{
  "type": "node",
  "id": 7602207796,
  "lat": 49.6200013,
  "lon": -1.6112218,
  "tags": {
    "bench": "yes",
    "bin": "no",
    "bus": "yes",
    "departures_board": "timetable",
    "highway": "bus_stop",
    "lit": "yes",
    "name": "La Ruche",
    "public_transport": "platform",
    "shelter": "yes",
    "tactile_paving": "yes"
  }
},
{
  "type": "node",
  "id": 7602207797,
  "lat": 49.6234127,
  "lon": -1.6136057,
  "tags": {
    "bench": "no",
    "bin": "no",
    "bus": "yes",
    "departures_board": "timetable",
    "highway": "bus_stop",
    "name": "Le Stade RN 13",
    "public_transport": "platform",
    "shelter": "no",
    "wheelchair": "yes"
  }
},
{
  "type": "node",
  "id": 7602207798,
  "lat": 49.6287147,
  "lon": -1.6182705,
  "tags": {
    "bus": "yes",
    "departures_board": "timetable",
    "highway": "bus_stop",
    "name": "Bosquet du Roule",
    "public_transport": "platform",
    "shelter": "yes"
  }
},
{
  "type": "node",
  "id": 7602207799,
  "lat": 49.6290395,
  "lon": -1.6180442,
  "tags": {
    "bus": "yes",
    "departures_board": "timetable",
    "highway": "bus_stop",
    "name": "Bosquet du Roule",
    "public_transport": "platform",
    "shelter": "yes"
  }
},
{
  "type": "node",
  "id": 7602207801,
  "lat": 49.6507891,
  "lon": -1.6515749,
  "tags": {
    "bus": "yes",
    "departures_board": "timetable",
    "highway": "bus_stop",
    "name": "Terrasse",
    "network": "Zephir Bus",
    "operator": "Aglo du Cotentin",
    "public_transport": "platform",
    "shelter": "no"
  }
},
{
  "type": "node",
  "id": 7605011048,
  "lat": 49.6037434,
  "lon": -1.6075973,
  "tags": {
    "bus": "yes",
    "departures_board": "timetable",
    "highway": "bus_stop",
    "name": "Genêts",
    "network": "Zephir Bus",
    "operator": "Aglo du Cotentin",
    "public_transport": "platform",
    "shelter": "yes"
  }
},
{
  "type": "node",
  "id": 7605011049,
  "lat": 49.6041083,
  "lon": -1.6086997,
  "tags": {
    "bus": "yes",
    "departures_board": "timetable",
    "highway": "bus_stop",
    "name": "Genêts",
    "public_transport": "platform",
    "shelter": "no"
  }
},
{
  "type": "node",
  "id": 7605011050,
  "lat": 49.6028028,
  "lon": -1.6051958,
  "tags": {
    "bus": "yes",
    "departures_board": "timetable",
    "highway": "bus_stop",
    "name": "Le Bocage",
    "public_transport": "platform",
    "shelter": "yes"
  }
},
{
  "type": "node",
  "id": 7605011051,
  "lat": 49.6023479,
  "lon": -1.6044800,
  "tags": {
    "bus": "yes",
    "departures_board": "timetable",
    "highway": "bus_stop",
    "name": "Le Bocage",
    "public_transport": "platform",
    "shelter": "no"
  }
},
{
  "type": "node",
  "id": 7605011052,
  "lat": 49.6360266,
  "lon": -1.5703617,
  "tags": {
    "bus": "yes",
    "departures_board": "timetable",
    "highway": "bus_stop",
    "name": "Les Flottes",
    "network": "Cap Cotentin",
    "operator": "Aglo du Cotentin",
    "public_transport": "platform",
    "shelter": "yes"
  }
},
{
  "type": "node",
  "id": 7605011053,
  "lat": 49.6366913,
  "lon": -1.5708834,
  "tags": {
    "bus": "yes",
    "departures_board": "timetable",
    "highway": "bus_stop",
    "name": "Les Flottes",
    "network": "Cap Cotentin",
    "network:wikidata": "Q3576504",
    "network:wikipedia": "fr:Transports en commun de Cherbourg-en-Cotentin",
    "operator": "Keolis Cherbourg",
    "public_transport": "platform",
    "shelter": "no"
  }
},
{
  "type": "node",
  "id": 7605011054,
  "lat": 49.6400056,
  "lon": -1.5717630,
  "tags": {
    "bus": "yes",
    "departures_board": "timetable",
    "highway": "bus_stop",
    "name": "La Place",
    "network": "Zephir Bus",
    "operator": "Aglo du Cotentin",
    "public_transport": "platform",
    "shelter": "yes"
  }
},
{
  "type": "node",
  "id": 7605011055,
  "lat": 49.6398531,
  "lon": -1.5713862,
  "tags": {
    "bus": "yes",
    "highway": "bus_stop",
    "name": "La Place",
    "network": "zephir Bus",
    "operator": "Aglo du Cotentin",
    "public_transport": "platform",
    "shelter": "no"
  }
},
{
  "type": "node",
  "id": 7605011057,
  "lat": 49.6340564,
  "lon": -1.6210470,
  "tags": {
    "bus": "yes",
    "departures_board": "timetable",
    "highway": "bus_stop",
    "name": "Cherbourg-en-Cotentin / Cherbourg – Autogare",
    "network": "Maneo",
    "operator": "Region Normandie",
    "public_transport": "platform",
    "shelter": "no"
  }
},
{
  "type": "node",
  "id": 7616495149,
  "lat": 49.6385510,
  "lon": -1.5439446,
  "tags": {
    "bus": "yes",
    "departures_board": "timetable",
    "highway": "bus_stop",
    "name": "Tourlaville - Le Val Canu",
    "network": "Maneo",
    "operator": "Region Normandie",
    "public_transport": "platform",
    "shelter": "no"
  }
},
{
  "type": "node",
  "id": 7616495150,
  "lat": 49.6383555,
  "lon": -1.5447336,
  "tags": {
    "bus": "yes",
    "departures_board": "timetable",
    "highway": "bus_stop",
    "name": "Tourlaville - Le Val Canu",
    "network": "Maneo",
    "operator": "Region Normandie",
    "public_transport": "platform",
    "shelter": "no"
  }
},
{
  "type": "node",
  "id": 8129088966,
  "lat": 49.6490217,
  "lon": -1.6530285,
  "tags": {
    "bus": "yes",
    "departures_board": "timetable",
    "highway": "bus_stop",
    "operator": "Keolis Cherbourg",
    "public_transport": "platform",
    "shelter": "yes"
  }
},
{
  "type": "node",
  "id": 8129088969,
  "lat": 49.6490035,
  "lon": -1.6584824,
  "tags": {
    "bus": "yes",
    "departures_board": "timetable",
    "highway": "bus_stop",
    "name": "Courbet",
    "public_transport": "platform",
    "shelter": "no"
  }
},
{
  "type": "node",
  "id": 8370783885,
  "lat": 49.6423262,
  "lon": -1.5839275,
  "tags": {
    "bench": "yes",
    "bin": "no",
    "bus": "yes",
    "departures_board": "timetable",
    "highway": "bus_stop",
    "name": "Fonderie",
    "network": "Cap Cotentin",
    "operator": "Communauté d'agglomération du Cotentin",
    "public_transport": "platform",
    "shelter": "yes",
    "wheelchair": "yes"
  }
},
{
  "type": "node",
  "id": 8370783886,
  "lat": 49.6422741,
  "lon": -1.5843018,
  "tags": {
    "bench": "no",
    "bin": "no",
    "bus": "yes",
    "departures_board": "timetable",
    "highway": "bus_stop",
    "name": "Fonderie",
    "network": "Cap Cotentin",
    "operator": "Communauté d'agglomération du Cotentin",
    "public_transport": "platform",
    "shelter": "no",
    "wheelchair": "yes"
  }
},
{
  "type": "node",
  "id": 8370783887,
  "lat": 49.6414033,
  "lon": -1.5791064,
  "tags": {
    "bench": "yes",
    "bin": "yes",
    "bus": "yes",
    "departures_board": "timetable",
    "highway": "bus_stop",
    "name": "Northeim",
    "network": "Cap Cotentin",
    "operator": "Communauté d'agglomération du Cotentin",
    "public_transport": "platform",
    "shelter": "yes",
    "wheelchair": "yes"
  }
},
{
  "type": "node",
  "id": 8370783888,
  "lat": 49.6405577,
  "lon": -1.5746816,
  "tags": {
    "bench": "yes",
    "bin": "yes",
    "bus": "yes",
    "departures_board": "timetable",
    "highway": "bus_stop",
    "name": "Grande Rue",
    "network": "Cap Cotentin",
    "operator": "Communauté d'agglomération du Cotentin",
    "public_transport": "platform",
    "shelter": "yes",
    "wheelchair": "yes"
  }
},
{
  "type": "node",
  "id": 8769050027,
  "lat": 49.6139034,
  "lon": -1.6029538,
  "tags": {
    "bench": "no",
    "bus": "yes",
    "departures_board": "timetable",
    "highway": "bus_stop",
    "name": "La Glacerie Mairie",
    "network": "Nomad",
    "public_transport": "platform",
    "shelter": "no",
    "wheelchair": "no"
  }
},
{
  "type": "node",
  "id": 9253335045,
  "lat": 49.6345218,
  "lon": -1.6537206,
  "tags": {
    "bus": "yes",
    "departures_board": "timetable",
    "highway": "bus_stop",
    "name": "Vindits",
    "network": "Cap Cotentin",
    "operator": "Communauté d'agglomération du Cotentin",
    "public_transport": "platform",
    "route_ref": "8;d",
    "type": "public_transport",
    "wheelchair": "yes"
  }
},
{
  "type": "node",
  "id": 9253335046,
  "lat": 49.6345230,
  "lon": -1.6525271,
  "tags": {
    "bus": "yes",
    "departures_board": "timetable",
    "highway": "bus_stop",
    "name": "Vindits",
    "network": "Cap Cotentin",
    "operator": "Communauté d'agglomération du Cotentin",
    "public_transport": "platform",
    "route_ref": "8",
    "wheelchair": "yes"
  }
},
{
  "type": "node",
  "id": 9380302673,
  "lat": 49.6629928,
  "lon": -1.6960869,
  "tags": {
    "bench": "no",
    "bin": "no",
    "bus": "yes",
    "departures_board": "timetable",
    "highway": "bus_stop",
    "name": "Epinay Haut",
    "network": "Cap Cotentin",
    "operator": "Communauté d'agglomération du Cotentin",
    "public_transport": "platform",
    "shelter": "no",
    "wheelchair": "yes"
  }
},
{
  "type": "node",
  "id": 9380302674,
  "lat": 49.6630206,
  "lon": -1.6969028,
  "tags": {
    "bench": "no",
    "bin": "no",
    "bus": "yes",
    "departures_board": "timetable",
    "highway": "bus_stop",
    "name": "Épinay Haut",
    "network": "Cap Cotentin",
    "operator": "Communauté d'agglomération du Cotentin",
    "public_transport": "platform",
    "shelter": "no",
    "wheelchair": "yes"
  }
},
{
  "type": "node",
  "id": 9385281461,
  "lat": 49.6413128,
  "lon": -1.5792276,
  "tags": {
    "bench": "yes",
    "bin": "no",
    "bus": "yes",
    "departures_board": "timetable",
    "highway": "bus_stop",
    "name": "Northeim",
    "network": "Cap Cotentin",
    "operator": "Communauté d'agglomération du Cotentin",
    "public_transport": "platform",
    "shelter": "yes",
    "wheelchair": "yes"
  }
},
{
  "type": "node",
  "id": 9385330832,
  "lat": 49.6406352,
  "lon": -1.5755353,
  "tags": {
    "bench": "no",
    "bin": "no",
    "bus": "yes",
    "departures_board": "timetable",
    "highway": "bus_stop",
    "name": "Grande Rue",
    "network": "Cap Cotentin",
    "operator": "Communauté d'agglomération du Cotentin",
    "public_transport": "platform",
    "shelter": "no",
    "wheelchair": "yes"
  }
},
{
  "type": "node",
  "id": 9385391619,
  "lat": 49.6490293,
  "lon": -1.5850978,
  "tags": {
    "bench": "yes",
    "bin": "no",
    "bus": "yes",
    "departures_board": "timetable",
    "highway": "bus_stop",
    "name": "Jean Goubert",
    "network": "Cap Cotentin",
    "operator": "Communauté d'agglomération du Cotentin",
    "public_transport": "platform",
    "shelter": "yes",
    "wheelchair": "yes"
  }
},
{
  "type": "node",
  "id": 9385394523,
  "lat": 49.6455814,
  "lon": -1.5837029,
  "tags": {
    "bench": "yes",
    "bin": "no",
    "bus": "yes",
    "departures_board": "timetable",
    "highway": "bus_stop",
    "name": "Europe",
    "network": "Cap Cotentin",
    "operator": "Communauté d'agglomération du Cotentin",
    "public_transport": "platform",
    "shelter": "yes",
    "wheelchair": "yes"
  }
},
{
  "type": "node",
  "id": 9385394524,
  "lat": 49.6456093,
  "lon": -1.5839619,
  "tags": {
    "bench": "no",
    "bin": "no",
    "bus": "yes",
    "departures_board": "timetable",
    "highway": "bus_stop",
    "name": "Europe",
    "network": "Cap Cotentin",
    "operator": "Communauté d'agglomération du Cotentin",
    "public_transport": "platform",
    "shelter": "no",
    "wheelchair": "yes"
  }
},
{
  "type": "node",
  "id": 9385426517,
  "lat": 49.6468418,
  "lon": -1.5908260,
  "tags": {
    "bench": "yes",
    "bin": "no",
    "bus": "yes",
    "departures_board": "timetable",
    "highway": "bus_stop",
    "name": "Clair Logis",
    "network": "Cap Cotentin",
    "operator": "Communauté d'agglomération du Cotentin",
    "public_transport": "platform",
    "shelter": "yes",
    "wheelchair": "yes"
  }
},
{
  "type": "node",
  "id": 9385426518,
  "lat": 49.6466568,
  "lon": -1.5909062,
  "tags": {
    "bench": "no",
    "bin": "no",
    "bus": "yes",
    "departures_board": "yes",
    "highway": "bus_stop",
    "name": "Clair Logis",
    "network": "Cap Cotentin",
    "operator": "Communauté d'agglomération du Cotentin",
    "public_transport": "platform",
    "shelter": "no",
    "wheelchair": "yes"
  }
},
{
  "type": "node",
  "id": 9385439759,
  "lat": 49.6397102,
  "lon": -1.6021754,
  "tags": {
    "bench": "no",
    "bin": "no",
    "bus": "yes",
    "departures_board": "timetable",
    "highway": "bus_stop",
    "name": "Guérranderie",
    "network": "Cap Cotentin",
    "operator": "Communauté d'agglomération du Cotentin",
    "public_transport": "platform",
    "shelter": "no",
    "wheelchair": "yes"
  }
},
{
  "type": "node",
  "id": 9450059993,
  "lat": 49.6576927,
  "lon": -1.6991150,
  "tags": {
    "highway": "bus_stop",
    "name": "Les Frênes",
    "public_transport": "platform"
  }
},
{
  "type": "node",
  "id": 9450059996,
  "lat": 49.6578194,
  "lon": -1.7025831,
  "tags": {
    "highway": "bus_stop",
    "name": "Le Bois",
    "public_transport": "platform"
  }
},
{
  "type": "node",
  "id": 9450155326,
  "lat": 49.6539203,
  "lon": -1.6812703,
  "tags": {
    "highway": "bus_stop",
    "name": "Carné",
    "public_transport": "platform",
    "shelter": "yes",
    "source": "cadastre-dgi-fr source : Direction Générale des Impôts - Cadastre. Mise à jour : 2014"
  }
},
{
  "type": "node",
  "id": 9450194910,
  "lat": 49.6529852,
  "lon": -1.6623420,
  "tags": {
    "bus": "yes",
    "departures_board": "timetable",
    "highway": "bus_stop",
    "name": "Prévert",
    "public_transport": "platform",
    "shelter": "no"
  }
},
{
  "type": "node",
  "id": 9450208923,
  "lat": 49.6542259,
  "lon": -1.6725625,
  "tags": {
    "bus": "yes",
    "departures_board": "timetable",
    "highway": "bus_stop",
    "name": "La Bonde",
    "public_transport": "platform",
    "shelter": "no"
  }
},
{
  "type": "node",
  "id": 9450308780,
  "lat": 49.6430783,
  "lon": -1.6516802,
  "tags": {
    "bench": "yes",
    "bin": "no",
    "bus": "yes",
    "departures_board": "timetable",
    "highway": "bus_stop",
    "lit": "yes",
    "name": "Val L'Abbé",
    "network": "Zephir Bus",
    "operator": "Keolis Cherbourg",
    "public_transport": "platform",
    "shelter": "yes",
    "tactile_paving": "yes"
  }
},
{
  "type": "node",
  "id": 9450308781,
  "lat": 49.6430662,
  "lon": -1.6514830,
  "tags": {
    "bench": "yes",
    "bin": "no",
    "bus": "yes",
    "departures_board": "timetable",
    "highway": "bus_stop",
    "lit": "yes",
    "name": "Val L'Abbé",
    "network": "Zephir Bus",
    "operator": "Keolis Cherbourg",
    "public_transport": "platform",
    "shelter": "yes",
    "tactile_paving": "yes"
  }
},
{
  "type": "node",
  "id": 9450329910,
  "lat": 49.6486568,
  "lon": -1.6525854,
  "tags": {
    "bus": "yes",
    "departures_board": "timetable",
    "highway": "bus_stop",
    "name": "Huit Mai",
    "public_transport": "platform",
    "shelter": "no"
  }
},
{
  "type": "node",
  "id": 9450329911,
  "lat": 49.6494148,
  "lon": -1.6543168,
  "tags": {
    "bus": "yes",
    "departures_board": "timetable",
    "highway": "bus_stop",
    "name": "Huit Mai",
    "public_transport": "platform",
    "source": "local knowledge",
    "wheelchair": "yes"
  }
},
{
  "type": "node",
  "id": 9450334450,
  "lat": 49.6428004,
  "lon": -1.6444315,
  "tags": {
    "bus": "yes",
    "departures_board": "timetable",
    "highway": "bus_stop",
    "name": "Charcot",
    "public_transport": "platform",
    "shelter": "no"
  }
},
{
  "type": "node",
  "id": 9450334451,
  "lat": 49.6428560,
  "lon": -1.6442344,
  "tags": {
    "bus": "yes",
    "departures_board": "timetable",
    "highway": "bus_stop",
    "name": "Charcot",
    "public_transport": "platform",
    "shelter": "no"
  }
},
{
  "type": "node",
  "id": 9450334463,
  "lat": 49.6423897,
  "lon": -1.6473578,
  "tags": {
    "bus": "yes",
    "departures_board": "timetable",
    "highway": "bus_stop",
    "name": "Lebas",
    "public_transport": "platform",
    "shelter": "no"
  }
},
{
  "type": "node",
  "id": 9450334464,
  "lat": 49.6424835,
  "lon": -1.6471298,
  "tags": {
    "bus": "yes",
    "departures_board": "timetable",
    "highway": "bus_stop",
    "name": "Lebas",
    "public_transport": "platform",
    "shelter": "yes"
  }
},
{
  "type": "node",
  "id": 9450334470,
  "lat": 49.6392571,
  "lon": -1.6513516,
  "tags": {
    "bus": "yes",
    "departures_board": "timetable",
    "highway": "bus_stop",
    "name": "Lecres",
    "public_transport": "platform",
    "shelter": "no"
  }
},
{
  "type": "node",
  "id": 9450334472,
  "lat": 49.6389696,
  "lon": -1.6521469,
  "tags": {
    "bus": "yes",
    "departures_board": "timetable",
    "highway": "bus_stop",
    "name": "Lecres",
    "public_transport": "platform",
    "shelter": "no"
  }
},
{
  "type": "node",
  "id": 9450334474,
  "lat": 49.6389748,
  "lon": -1.6536824,
  "tags": {
    "bus": "yes",
    "departures_board": "timetable",
    "highway": "bus_stop",
    "name": "Frachon",
    "public_transport": "platform",
    "shelter": "yes"
  }
},
{
  "type": "node",
  "id": 9450334481,
  "lat": 49.6420597,
  "lon": -1.6528375,
  "tags": {
    "bus": "yes",
    "departures_board": "timetable",
    "highway": "bus_stop",
    "name": "Schmitt",
    "network": "Zephir Bus",
    "operator": "Keolis Cherbourg",
    "public_transport": "platform",
    "shelter": "no"
  }
},
{
  "type": "node",
  "id": 9450334482,
  "lat": 49.6422290,
  "lon": -1.6528268,
  "tags": {
    "bus": "yes",
    "departures_board": "timetable",
    "highway": "bus_stop",
    "name": "Schmitt",
    "network": "Zephir Bus",
    "operator": "Keolis Cherbourg",
    "public_transport": "platform",
    "shelter": "no"
  }
},
{
  "type": "node",
  "id": 9450850872,
  "lat": 49.6081602,
  "lon": -1.6114470,
  "tags": {
    "bench": "no",
    "bin": "no",
    "bus": "yes",
    "highway": "bus_stop",
    "name": "Les Renardières",
    "public_transport": "platform",
    "ref": "4",
    "shelter": "no"
  }
},
{
  "type": "node",
  "id": 9472547342,
  "lat": 49.6484662,
  "lon": -1.6534585,
  "tags": {
    "departures_board": "timetable",
    "highway": "bus_stop",
    "name": "Huit Mai",
    "public_transport": "platform",
    "shelter": "no"
  }
},
{
  "type": "node",
  "id": 9472547343,
  "lat": 49.6472987,
  "lon": -1.6560844,
  "tags": {
    "bench": "no",
    "departures_board": "timetable",
    "highway": "bus_stop",
    "name": "Belgique",
    "public_transport": "platform",
    "shelter": "no"
  }
},
{
  "type": "node",
  "id": 9472547344,
  "lat": 49.6473526,
  "lon": -1.6561916,
  "tags": {
    "bench": "no",
    "departures_board": "timetable",
    "highway": "bus_stop",
    "name": "Belgique",
    "public_transport": "platform",
    "shelter": "no"
  }
}

  ]
}
